<cockatrice_carddatabase version="4">
  <sets>
    <set>
      <name>DM23-RP2</name>
      <longname>DM23-RP2</longname>
      <settype>DM23-RP2</settype>
      <releasedate>2023-11-05</releasedate>
    </set>
  </sets>
  <cards>
    <card>
      <name>Perfect Earth, Planetary Dragon</name>
      <text>
■ Double Breaker
■ Each card put into your hand from your shield zone gets "shield trigger".
  </text>
      <prop>
        <maintype>Creature</maintype>
        <type>World Dragon</type>
        <manacost>5</manacost>
        <colors>Light/Water/Darkness/Fire/Nature</colors>
        <pt>6000</pt>
      </prop>
      <set num="DM23-RP2-TR7">DM23-RP2</set>
      <related></related>
      <tablerow>2</tablerow>
    </card>
    <card>
      <name>Savage Earth</name>
      <text>
■ Put a non-evolution creature from your mana zone. Choose a non-evolution creature from your opponent's mana zone and your opponent puts it. Then choose one of your creatures and one of your opponent's creatures from the battle zone and put them into their owner's mana zones.
  </text>
      <prop>
        <maintype>Spell</maintype>
        <type></type>
        <manacost>8</manacost>
        <colors>Nature</colors>
        <pt></pt>
      </prop>
      <set num="DM23-RP2-SP2">DM23-RP2</set>
      <related></related>
      <tablerow>2</tablerow>
    </card>
    <card>
      <name>Oriotis Judge</name>
      <text>
■ Shield Trigger
■ Each player puts all their creatures that cost the same as or more than the number of cards in their mana zones on the bottom of their decks in any order.
  </text>
      <prop>
        <maintype>Spell</maintype>
        <type></type>
        <manacost>3</manacost>
        <colors>Light</colors>
        <pt></pt>
      </prop>
      <set num="DM23-RP2-T3">DM23-RP2</set>
      <related></related>
      <tablerow>2</tablerow>
    </card>
    <card>
      <name>Oriotis Judge</name>
      <text>
■ Shield Trigger
■ Each player puts all their creatures that cost the same as or more than the number of cards in their mana zones on the bottom of their decks in any order.
  </text>
      <prop>
        <maintype>Spell</maintype>
        <type></type>
        <manacost>3</manacost>
        <colors>Light</colors>
        <pt></pt>
      </prop>
      <set num="DM23-RP2- TF3">DM23-RP2</set>
      <related></related>
      <tablerow>2</tablerow>
    </card>
    <card>
      <name>Gachidive, Eureka</name>
      <text>
■ Evolution—Put on one of your water creatures.
■ Invasion
■ Double Breaker
■ When you put this creature, you may put a creature from your hand under this creature. If you do, draw 2 cards.
  </text>
      <prop>
        <maintype>Evolution Creature</maintype>
        <type>Magic Command/Great Mecha King/Invader</type>
        <manacost>5</manacost>
        <colors>Water</colors>
        <pt>6000</pt>
      </prop>
      <set num="DM23-RP2-T4">DM23-RP2</set>
      <related></related>
      <tablerow>2</tablerow>
    </card>
    <card>
      <name>Gachidive, Eureka</name>
      <text>
■ Evolution—Put on one of your water creatures.
■ Invasion
■ Double Breaker
■ When you put this creature, you may put a creature from your hand under this creature. If you do, draw 2 cards.
  </text>
      <prop>
        <maintype>Evolution Creature</maintype>
        <type>Magic Command/Great Mecha King/Invader</type>
        <manacost>5</manacost>
        <colors>Water</colors>
        <pt>6000</pt>
      </prop>
      <set num="DM23-RP2- TF4">DM23-RP2</set>
      <related></related>
      <tablerow>2</tablerow>
    </card>
    <card>
      <name>Puchohenza, Mia Moja</name>
      <text>
■ Revolution Change: Light or Nature Dragon that costs 5 or more
■ Triple Breaker
■ Your opponent's creatures that cost less than the number of cards in your mana zone are put tapped.
■ Final Revolution: When you put this creature with "Revolution Change" and you haven't used another "Final Revolution" during this turn, put all creatures that have power less than this creature into their owner's mana zones.
  </text>
      <prop>
        <maintype>Creature</maintype>
        <type>Jurassic Command Dragon/Revolutionary/Team Damama</type>
        <manacost>8</manacost>
        <colors>Light/Nature</colors>
        <pt>12500</pt>
      </prop>
      <set num="DM23-RP2-SP1">DM23-RP2</set>
      <related></related>
      <tablerow>2</tablerow>
    </card>
    <card>
      <name>Georges Bataille</name>
      <text>
■ You may destroy 4 of your creatures instead of paying this creature's cost.
■ Triple Breaker
■ When you put this creature into the battle zone, count the number of cards in your graveyard. You may put the same number of cards from the top of your deck into your graveyard.
■ When this creature would leave, you may put 6 cards from your graveyard on the bottom of your deck instead.
  </text>
      <prop>
        <maintype>Creature</maintype>
        <type>Mafi Gang</type>
        <manacost>8</manacost>
        <colors>Darkness</colors>
        <pt>12000</pt>
      </prop>
      <set num="DM23-RP2-TR6">DM23-RP2</set>
      <related></related>
      <tablerow>2</tablerow>
    </card>
    <card>
      <name>Stepple, Cherry Blossom Wind Faerie</name>
      <text>
■ When you put this creature into the battle zone, put the top card of your deck into your mana zone.
■ When this creature is destroyed, put a card from your mana zone into your graveyard.
  </text>
      <prop>
        <maintype>Creature</maintype>
        <type>Snow Faerie</type>
        <manacost>2</manacost>
        <colors>Nature</colors>
        <pt>1000</pt>
      </prop>
      <set num="DM23-RP2-T8">DM23-RP2</set>
      <related></related>
      <tablerow>2</tablerow>
    </card>
    <card>
      <name>Stepple, Cherry Blossom Wind Faerie</name>
      <text>
■ When you put this creature into the battle zone, put the top card of your deck into your mana zone.
■ When this creature is destroyed, put a card from your mana zone into your graveyard.
  </text>
      <prop>
        <maintype>Creature</maintype>
        <type>Snow Faerie</type>
        <manacost>2</manacost>
        <colors>Nature</colors>
        <pt>1000</pt>
      </prop>
      <set num="DM23-RP2- TF8">DM23-RP2</set>
      <related></related>
      <tablerow>2</tablerow>
    </card>
    <card>
      <name>Gayoushin</name>
      <text>
■ When you put this creature, if you have 5 or more Jokers in the battle zone or mana zone, draw 2 cards. Then you may discard a Jokers from your hand. If you do, draw 2 cards.
  </text>
      <prop>
        <maintype>Creature</maintype>
        <type>Jokers/Specials</type>
        <manacost>5</manacost>
        <colors>Colorless</colors>
        <pt>4000</pt>
      </prop>
      <set num="DM23-RP2-TR2">DM23-RP2</set>
      <related></related>
      <tablerow>2</tablerow>
    </card>
    <card>
      <name>Kuromame Danshaku/Hakumai Danshaku</name>
      <text>
■ Triple Breaker
■ Whenever your opponent puts a creature with an ability that starts with "When you put this creature into the battle zone"
=========================
■ Put the top card of your deck into your mana zone. Then you may return a card from your mana zone to your hand.
  </text>
      <prop>
        <maintype>Twinpact</maintype>
        <type>Gransect/Specials</type>
        <manacost>8</manacost>
        <colors>Nature/Nature</colors>
        <pt>12000</pt>
      </prop>
      <set num="DM23-RP2-TR9">DM23-RP2</set>
      <related></related>
      <tablerow>2</tablerow>
    </card>
    <card>
      <name>卍 Grand Zero 卍</name>
      <text>
■ Whenever you cast a Magic Tool spell, instead of putting it into your graveyard after you cast, you may put it under this field and draw a card.
■ Ignore any effects that would prevent you from casting Magic Tool spells or Dolszak spells.
■ Gate of Moonless Night 99: At the End Step
  </text>
      <prop>
        <maintype>Moonless Night Field</maintype>
        <type></type>
        <manacost>2</manacost>
        <colors>Water</colors>
        <pt></pt>
      </prop>
      <set num="DM23-RP2-SP3">DM23-RP2</set>
      <related></related>
      <tablerow>2</tablerow>
    </card>
    <card>
      <name>Gekabankai Ga Ryumizu 卍</name>
      <text>
■ You may summon up to 4 Dolszaks from your hand or graveyard for no cost.
■ Take an extra turn after this one.
  </text>
      <prop>
        <maintype>Spell</maintype>
        <type>Dolszak</type>
        <manacost>99</manacost>
        <colors>Water</colors>
        <pt></pt>
      </prop>
      <set num="DM23-RP2-TR4">DM23-RP2</set>
      <related></related>
      <tablerow>2</tablerow>
    </card>
    <card>
      <name>Deddam, Disaster</name>
      <text>
■ When you put this creature, look at the top 3 cards of your deck. Put one of them into your hand, one into your mana zone and one into your graveyard.
  </text>
      <prop>
        <maintype>Creature</maintype>
        <type>Trinity Command/Invader</type>
        <manacost>3</manacost>
        <colors>Water/Darkness/Nature</colors>
        <pt>3000</pt>
      </prop>
      <set num="DM23-RP2-T7">DM23-RP2</set>
      <related></related>
      <tablerow>2</tablerow>
    </card>
    <card>
      <name>Deddam, Disaster</name>
      <text>
■ When you put this creature, look at the top 3 cards of your deck. Put one of them into your hand, one into your mana zone and one into your graveyard.
  </text>
      <prop>
        <maintype>Creature</maintype>
        <type>Trinity Command/Invader</type>
        <manacost>3</manacost>
        <colors>Water/Darkness/Nature</colors>
        <pt>3000</pt>
      </prop>
      <set num="DM23-RP2- TF7">DM23-RP2</set>
      <related></related>
      <tablerow>2</tablerow>
    </card>
    <card>
      <name>Perfect Fire</name>
      <text>
■ Choose 2 of the following. ''(You may choose the same one twice.)''
:► Put a creature that costs 3 or less from your hand.
:► One of your creatures gets "speed attacker" until the End Step
  </text>
      <prop>
        <maintype>Spell</maintype>
        <type></type>
        <manacost>3</manacost>
        <colors>Fire</colors>
        <pt></pt>
      </prop>
      <set num="DM23-RP2-TR8">DM23-RP2</set>
      <related></related>
      <tablerow>2</tablerow>
    </card>
    <card>
      <name>Mage of Cursebreaker</name>
      <text>
■ Shield Trigger
■ Blocker
■ When you put this creature, you may put shieldify a card from your hand face up.
  </text>
      <prop>
        <maintype>Creature</maintype>
        <type>Metallica/Team Ginga</type>
        <manacost>7</manacost>
        <colors>Light/Water</colors>
        <pt>2000</pt>
      </prop>
      <set num="DM23-RP2-T5">DM23-RP2</set>
      <related></related>
      <tablerow>2</tablerow>
    </card>
    <card>
      <name>Mage of Cursebreaker</name>
      <text>
■ Shield Trigger
■ Blocker
■ When you put this creature, you may put shieldify a card from your hand face up.
  </text>
      <prop>
        <maintype>Creature</maintype>
        <type>Metallica/Team Ginga</type>
        <manacost>7</manacost>
        <colors>Light/Water</colors>
        <pt>2000</pt>
      </prop>
      <set num="DM23-RP2- TF5">DM23-RP2</set>
      <related></related>
      <tablerow>2</tablerow>
    </card>
    <card>
      <name>Walkure Lupia, Sky Lord Dragonmech</name>
      <text>
■ Revolution Change: Fire Bird or Dragon ''(When one of your Fire Birds or Dragons attacks, you may switch that creature with this creature from your hand.)''
■ Double Breaker
■ Each of your Fire Birds gets "speed attacker". ''(A creature that has "speed attacker" doesn't get summoning sickness.)''
■ Each of your Dragons gets "blocker". ''(You may tap a creature that has "blocker" to change the attack target of your opponent's creature to that creature.)''
  </text>
      <prop>
        <maintype>Creature</maintype>
        <type>Fire Bird/Armored Dragon</type>
        <manacost>5</manacost>
        <colors>Light/Fire</colors>
        <pt>6000</pt>
      </prop>
      <set num="DM23-RP2-T6">DM23-RP2</set>
      <related></related>
      <tablerow>2</tablerow>
    </card>
    <card>
      <name>Walkure Lupia, Sky Lord Dragonmech</name>
      <text>
■ Revolution Change: Fire Bird or Dragon ''(When one of your Fire Birds or Dragons attacks, you may switch that creature with this creature from your hand.)''
■ Double Breaker
■ Each of your Fire Birds gets "speed attacker". ''(A creature that has "speed attacker" doesn't get summoning sickness.)''
■ Each of your Dragons gets "blocker". ''(You may tap a creature that has "blocker" to change the attack target of your opponent's creature to that creature.)''
  </text>
      <prop>
        <maintype>Creature</maintype>
        <type>Fire Bird/Armored Dragon</type>
        <manacost>5</manacost>
        <colors>Light/Fire</colors>
        <pt>6000</pt>
      </prop>
      <set num="DM23-RP2- TF6">DM23-RP2</set>
      <related></related>
      <tablerow>2</tablerow>
    </card>
    <card>
      <name>Basilisk, Blue Dragon of the Hideaway Hidden Blade</name>
      <text>
■ Ninja Strike
■ Blocker
■ Double Breaker
■ Whenever you put a Shinobi, choose one of your opponent's creatures. Until the start of your next turn, that creature can't attack or block.
  </text>
      <prop>
        <maintype>Creature</maintype>
        <type>Shinobi Dragon/Origin</type>
        <manacost>6</manacost>
        <colors>Water</colors>
        <pt>6000</pt>
      </prop>
      <set num="DM23-RP2-TR3">DM23-RP2</set>
      <related></related>
      <tablerow>2</tablerow>
    </card>
    <card>
      <name>Kakushi Recipe, Hideaway Hidden Blade</name>
      <text>
■ Ninja Strike
■ When you put this creature, choose one of your opponent's creatures. Until the start of your next turn, that creature can't attack or block.
  </text>
      <prop>
        <maintype>Creature</maintype>
        <type>Splash Queen/Shinobi</type>
        <manacost>4</manacost>
        <colors>Water</colors>
        <pt>3000</pt>
      </prop>
      <set num="DM23-RP2-T9">DM23-RP2</set>
      <related></related>
      <tablerow>2</tablerow>
    </card>
    <card>
      <name>Kakushi Recipe, Hideaway Hidden Blade</name>
      <text>
■ Ninja Strike
■ When you put this creature, choose one of your opponent's creatures. Until the start of your next turn, that creature can't attack or block.
  </text>
      <prop>
        <maintype>Creature</maintype>
        <type>Splash Queen/Shinobi</type>
        <manacost>4</manacost>
        <colors>Water</colors>
        <pt>3000</pt>
      </prop>
      <set num="DM23-RP2- TF9">DM23-RP2</set>
      <related></related>
      <tablerow>2</tablerow>
    </card>
    <card>
      <name>Balad Vi Na Shura</name>
      <text>
■ When you would Prevents Defeat
■ Speed Attacker
■ Double Breaker
■ File:Oniend.png
  </text>
      <prop>
        <maintype>Creature</maintype>
        <type>Demonio/Onifuda Kingdom</type>
        <manacost>5</manacost>
        <colors>Darkness/Fire</colors>
        <pt>6000</pt>
      </prop>
      <set num="DM23-RP2-SP5">DM23-RP2</set>
      <related></related>
      <tablerow>2</tablerow>
    </card>
    <card>
      <name>Piouspatrol Police</name>
      <text>
■ Galaxyshield
■ Galaxy Go
■ When you put this creature face up into your shield zone, choose a creature that costs 2 or less and return it to its owner's hand. During your opponent's next turn, your opponent can't summon creatures that cost 2 or less.
  </text>
      <prop>
        <maintype>Creature</maintype>
        <type>Metallica/Team Ginga</type>
        <manacost>4</manacost>
        <colors>Water</colors>
        <pt>4000</pt>
      </prop>
      <set num="DM23-RP2-SP4">DM23-RP2</set>
      <related></related>
      <tablerow>2</tablerow>
    </card>
    <card>
      <name>Summer! Duema Training!!</name>
      <text>
■ Discard your hand, draw 4 cards, then put a card into your mana zone.
■ If it's your turn, skip the rest of the turn.
  </text>
      <prop>
        <maintype>Spell</maintype>
        <type></type>
        <manacost>3</manacost>
        <colors>Water/Fire/Nature</colors>
        <pt></pt>
      </prop>
      <set num="DM23-RP2-T2">DM23-RP2</set>
      <related></related>
      <tablerow>2</tablerow>
    </card>
    <card>
      <name>Summer! Duema Training!!</name>
      <text>
■ Discard your hand, draw 4 cards, then put a card into your mana zone.
■ If it's your turn, skip the rest of the turn.
  </text>
      <prop>
        <maintype>Spell</maintype>
        <type></type>
        <manacost>3</manacost>
        <colors>Water/Fire/Nature</colors>
        <pt></pt>
      </prop>
      <set num="DM23-RP2- TF2">DM23-RP2</set>
      <related></related>
      <tablerow>2</tablerow>
    </card>
    <card>
      <name>Comeback Atchaaa!!</name>
      <text>
■ Gravity Zero
■ Put a fire creature that costs 7 or less from your hyperspatial zone. That creature breaks one of your opponent's shields.
  </text>
      <prop>
        <maintype>Spell</maintype>
        <type></type>
        <manacost>7</manacost>
        <colors>Fire</colors>
        <pt></pt>
      </prop>
      <set num="DM23-RP2-T1">DM23-RP2</set>
      <related></related>
      <tablerow>2</tablerow>
    </card>
    <card>
      <name>Comeback Atchaaa!!</name>
      <text>
■ Gravity Zero
■ Put a fire creature that costs 7 or less from your hyperspatial zone. That creature breaks one of your opponent's shields.
  </text>
      <prop>
        <maintype>Spell</maintype>
        <type></type>
        <manacost>7</manacost>
        <colors>Fire</colors>
        <pt></pt>
      </prop>
      <set num="DM23-RP2- TF1">DM23-RP2</set>
      <related></related>
      <tablerow>2</tablerow>
    </card>
    <card>
      <name>Katta Kirifuda %26 Katsuking -Story of Passion-</name>
      <text>
■ Mach Fighter
■ When you put this creature, look at the top 5 cards of your deck. Reveal one to your opponent, add it to your hand, and put the rest on the bottom of your deck in any order. If the revealed card is fire or nature, you may choose a creature and return it to its owner's hand.
■ Revolution 2: If you have 2 shields or less, this creature gets "shield trigger" in your shield zone.
■ Revolution 0: If you have no shields, this creature gets +10000 power, "speed attacker" and "triple breaker".
  </text>
      <prop>
        <maintype>Creature</maintype>
        <type>Outrage Dragon/Human</type>
        <manacost>5</manacost>
        <colors>Water/Fire/Nature</colors>
        <pt>5000+</pt>
      </prop>
      <set num="DM23-RP2-TR1">DM23-RP2</set>
      <related></related>
      <tablerow>2</tablerow>
    </card>
    <card>
      <name>Supernova DOOM Dragerion</name>
      <text>
■ This creature costs 1 less to summon for each creature this creature Evolution Source
■ Super Infinite Graveyard evolution: Put this creature on one or more of your creatures from your graveyard.
■ Triple Breaker
■ Meteorburn: Whenever this creature attacks, you may put a card under this creature into your graveyard. If you do, choose one of your opponent's creatures. That chosen creature gets -9000 power until the End Step
  </text>
      <prop>
        <maintype>Evolution Creature</maintype>
        <type>Phoenix/Demon Command/Zombie Dragon</type>
        <manacost>12</manacost>
        <colors>Darkness</colors>
        <pt>12000</pt>
      </prop>
      <set num="DM23-RP2-TR5">DM23-RP2</set>
      <related></related>
      <tablerow>2</tablerow>
    </card>
    <card>
      <name>Cloud Giant</name>
      <text>
■ When you put this creature, reveal the top 3 cards of your deck. Put all Giants from among them into your mana zone tapped and put the rest on the bottom of your deck in any order.
  </text>
      <prop>
        <maintype>Creature</maintype>
        <type>Giant</type>
        <manacost>4</manacost>
        <colors>Nature</colors>
        <pt>4000</pt>
      </prop>
      <set num="DM23-RP2-T10">DM23-RP2</set>
      <related></related>
      <tablerow>2</tablerow>
    </card>
    <card>
      <name>Cloud Giant</name>
      <text>
■ When you put this creature, reveal the top 3 cards of your deck. Put all Giants from among them into your mana zone tapped and put the rest on the bottom of your deck in any order.
  </text>
      <prop>
        <maintype>Creature</maintype>
        <type>Giant</type>
        <manacost>4</manacost>
        <colors>Nature</colors>
        <pt>4000</pt>
      </prop>
      <set num="DM23-RP2- TF10">DM23-RP2</set>
      <related></related>
      <tablerow>2</tablerow>
    </card>
    <card>
      <name>Jenny, Beautiful Delivery Doll</name>
      <text>
■ When you put this creature, your opponent chooses a card from their hand and discards it.
  </text>
      <prop>
        <maintype>Creature</maintype>
        <type>Death Puppet</type>
        <manacost>2</manacost>
        <colors>Darkness</colors>
        <pt>1000</pt>
      </prop>
      <set num="DM23-RP2-65">DM23-RP2</set>
      <related></related>
      <tablerow>2</tablerow>
    </card>
    <card>
      <name>Jenny, Beautiful Delivery Doll</name>
      <text>
■ When you put this creature, your opponent chooses a card from their hand and discards it.
  </text>
      <prop>
        <maintype>Creature</maintype>
        <type>Death Puppet</type>
        <manacost>2</manacost>
        <colors>Darkness</colors>
        <pt>1000</pt>
      </prop>
      <set num="DM23-RP2- 20B">DM23-RP2</set>
      <related></related>
      <tablerow>2</tablerow>
    </card>
    <card>
      <name>Jenny, Beautiful Delivery Doll</name>
      <text>
■ When you put this creature, your opponent chooses a card from their hand and discards it.
  </text>
      <prop>
        <maintype>Creature</maintype>
        <type>Death Puppet</type>
        <manacost>2</manacost>
        <colors>Darkness</colors>
        <pt>1000</pt>
      </prop>
      <set num="DM23-RP2- 18A">DM23-RP2</set>
      <related></related>
      <tablerow>2</tablerow>
    </card>
    <card>
      <name>Happou, Persevering Holy Chaos</name>
      <text>
■ Shield Trigger Plus
■ Blocker
■ Icon
  </text>
      <prop>
        <maintype>Creature</maintype>
        <type>Mecha Del Stella/Shinobi</type>
        <manacost>2</manacost>
        <colors>Light</colors>
        <pt>2500</pt>
      </prop>
      <set num="DM23-RP2-53">DM23-RP2</set>
      <related></related>
      <tablerow>2</tablerow>
    </card>
    <card>
      <name>Suiton, Water Cloud Holy Chaos</name>
      <text>
■ Shield Trigger Plus
■ Whenever you put a creature, choose one of your opponent's creatures and tap it.
■ Icon
  </text>
      <prop>
        <maintype>Creature</maintype>
        <type>Mecha Del Stella/Shinobi</type>
        <manacost>5</manacost>
        <colors>Light</colors>
        <pt>4000</pt>
      </prop>
      <set num="DM23-RP2-11">DM23-RP2</set>
      <related></related>
      <tablerow>2</tablerow>
    </card>
    <card>
      <name>Kusokzeshki, Holy Chaos Great Ninja</name>
      <text>
■ Shield Trigger Plus
■ Icon
■ Blocker
■ Each of your Mecha creatures that cost 8 or less in your shield zone get "Shield Trigger".
  </text>
      <prop>
        <maintype>Creature</maintype>
        <type>Mecha Del Stella/Shinobi</type>
        <manacost>5</manacost>
        <colors>Light</colors>
        <pt>5500</pt>
      </prop>
      <set num="DM23-RP2-2">DM23-RP2</set>
      <related></related>
      <tablerow>2</tablerow>
    </card>
    <card>
      <name>Sith, Wicked Fight</name>
      <text>
■ Abyss Rush
■ Double Breaker
■ When you put this creature, choose one of your opponent's creatures. That creature loses infinite power until the End Step
■ Whenever this creature attacks, you may Mechraid
  </text>
      <prop>
        <maintype>Creature</maintype>
        <type>Abyss Chimera</type>
        <manacost>6</manacost>
        <colors>Darkness</colors>
        <pt>9000</pt>
      </prop>
      <set num="DM23-RP2-OR2">DM23-RP2</set>
      <related></related>
      <tablerow>2</tablerow>
    </card>
    <card>
      <name>Sith, Wicked Fight</name>
      <text>
■ Abyss Rush
■ Double Breaker
■ When you put this creature, choose one of your opponent's creatures. That creature loses infinite power until the End Step
■ Whenever this creature attacks, you may Mechraid
  </text>
      <prop>
        <maintype>Creature</maintype>
        <type>Abyss Chimera</type>
        <manacost>6</manacost>
        <colors>Darkness</colors>
        <pt>9000</pt>
      </prop>
      <set num="DM23-RP2- 2S">DM23-RP2</set>
      <related></related>
      <tablerow>2</tablerow>
    </card>
    <card>
      <name>Sith, Wicked Fight</name>
      <text>
■ Abyss Rush
■ Double Breaker
■ When you put this creature, choose one of your opponent's creatures. That creature loses infinite power until the End Step
■ Whenever this creature attacks, you may Mechraid
  </text>
      <prop>
        <maintype>Creature</maintype>
        <type>Abyss Chimera</type>
        <manacost>6</manacost>
        <colors>Darkness</colors>
        <pt>9000</pt>
      </prop>
      <set num="DM23-RP2- 2B">DM23-RP2</set>
      <related></related>
      <tablerow>2</tablerow>
    </card>
    <card>
      <name>Chaosmantra, Holy</name>
      <text>
■ Ninja Change
■ Double Breaker
■ When you put this creature or whenever it attacks, tap all your opponent's creatures.
■ Your opponent's creatures can't attack the turn they are put.
  </text>
      <prop>
        <maintype>Creature</maintype>
        <type>Mecha Del Stella/Shinobi</type>
        <manacost>7</manacost>
        <colors>Light</colors>
        <pt>9500</pt>
      </prop>
      <set num="DM23-RP2-OR1">DM23-RP2</set>
      <related></related>
      <tablerow>2</tablerow>
    </card>
    <card>
      <name>Chaosmantra, Holy</name>
      <text>
■ Ninja Change
■ Double Breaker
■ When you put this creature or whenever it attacks, tap all your opponent's creatures.
■ Your opponent's creatures can't attack the turn they are put.
  </text>
      <prop>
        <maintype>Creature</maintype>
        <type>Mecha Del Stella/Shinobi</type>
        <manacost>7</manacost>
        <colors>Light</colors>
        <pt>9500</pt>
      </prop>
      <set num="DM23-RP2- 1S">DM23-RP2</set>
      <related></related>
      <tablerow>2</tablerow>
    </card>
    <card>
      <name>Chaosmantra, Holy</name>
      <text>
■ Ninja Change
■ Double Breaker
■ When you put this creature or whenever it attacks, tap all your opponent's creatures.
■ Your opponent's creatures can't attack the turn they are put.
  </text>
      <prop>
        <maintype>Creature</maintype>
        <type>Mecha Del Stella/Shinobi</type>
        <manacost>7</manacost>
        <colors>Light</colors>
        <pt>9500</pt>
      </prop>
      <set num="DM23-RP2- 1B">DM23-RP2</set>
      <related></related>
      <tablerow>2</tablerow>
    </card>
    <card>
      <name>Senju, Lasting Moment Holy Chaos</name>
      <text>
■ Gravity Zero
  </text>
      <prop>
        <maintype>Creature</maintype>
        <type>Mecha Del Stella/Shinobi</type>
        <manacost>5</manacost>
        <colors>Light</colors>
        <pt>2000</pt>
      </prop>
      <set num="DM23-RP2-52">DM23-RP2</set>
      <related></related>
      <tablerow>2</tablerow>
    </card>
    <card>
      <name>Ga:Nateha</name>
      <text>
■ Blocker
■ Slayer
■ At the start of your turn, you may put 2 of your shields into your graveyard. If you do, Abyss Mechraid 8. Mechraid
  </text>
      <prop>
        <maintype>Creature</maintype>
        <type>Noir Abyss</type>
        <manacost>4</manacost>
        <colors>Darkness</colors>
        <pt>4000</pt>
      </prop>
      <set num="DM23-RP2-17">DM23-RP2</set>
      <related></related>
      <tablerow>2</tablerow>
    </card>
    <card>
      <name>Ga:Nateha</name>
      <text>
■ Blocker
■ Slayer
■ At the start of your turn, you may put 2 of your shields into your graveyard. If you do, Abyss Mechraid 8. Mechraid
  </text>
      <prop>
        <maintype>Creature</maintype>
        <type>Noir Abyss</type>
        <manacost>4</manacost>
        <colors>Darkness</colors>
        <pt>4000</pt>
      </prop>
      <set num="DM23-RP2- 16B">DM23-RP2</set>
      <related></related>
      <tablerow>2</tablerow>
    </card>
    <card>
      <name>Ga:Nateha</name>
      <text>
■ Blocker
■ Slayer
■ At the start of your turn, you may put 2 of your shields into your graveyard. If you do, Abyss Mechraid 8. Mechraid
  </text>
      <prop>
        <maintype>Creature</maintype>
        <type>Noir Abyss</type>
        <manacost>4</manacost>
        <colors>Darkness</colors>
        <pt>4000</pt>
      </prop>
      <set num="DM23-RP2- 14A">DM23-RP2</set>
      <related></related>
      <tablerow>2</tablerow>
    </card>
    <card>
      <name>Telesco %3D Teles, Forethought</name>
      <text>
■ Blocker
■ Powered Breaker
■ At the start of your opponent's turn, your opponent discards a card at random from their hand.
■ Whenever your opponent discards a card from their hand, you may draw a card.
■ This creature gets +5000 power for each player that has no cards in their hand.
  </text>
      <prop>
        <maintype>Creature</maintype>
        <type>Abyss Royale</type>
        <manacost>5</manacost>
        <colors>Darkness</colors>
        <pt>5000+</pt>
      </prop>
      <set num="DM23-RP2-5">DM23-RP2</set>
      <related></related>
      <tablerow>2</tablerow>
    </card>
    <card>
      <name>Telesco %3D Teles, Forethought</name>
      <text>
■ Blocker
■ Powered Breaker
■ At the start of your opponent's turn, your opponent discards a card at random from their hand.
■ Whenever your opponent discards a card from their hand, you may draw a card.
■ This creature gets +5000 power for each player that has no cards in their hand.
  </text>
      <prop>
        <maintype>Creature</maintype>
        <type>Abyss Royale</type>
        <manacost>5</manacost>
        <colors>Darkness</colors>
        <pt>5000+</pt>
      </prop>
      <set num="DM23-RP2- 12B">DM23-RP2</set>
      <related></related>
      <tablerow>2</tablerow>
    </card>
    <card>
      <name>Telesco %3D Teles, Forethought</name>
      <text>
■ Blocker
■ Powered Breaker
■ At the start of your opponent's turn, your opponent discards a card at random from their hand.
■ Whenever your opponent discards a card from their hand, you may draw a card.
■ This creature gets +5000 power for each player that has no cards in their hand.
  </text>
      <prop>
        <maintype>Creature</maintype>
        <type>Abyss Royale</type>
        <manacost>5</manacost>
        <colors>Darkness</colors>
        <pt>5000+</pt>
      </prop>
      <set num="DM23-RP2- 10A">DM23-RP2</set>
      <related></related>
      <tablerow>2</tablerow>
    </card>
    <card>
      <name>Perfect Mysticroar</name>
      <text>
■ If you have 4 or more cards in your mana zone that cost 7 or more, this spell costs 2 less to cast.
■ Choose 2 of the following. ''(You may choose the same one twice.)''
:► Draw 2 cards.
:► Choose one of your opponent's creatures and put it into it's owner's mana zone.
:► Shuffle your deck, then reveal the top card. If it's a creature, put it.
  </text>
      <prop>
        <maintype>Spell</maintype>
        <type></type>
        <manacost>8</manacost>
        <colors>Water/Nature</colors>
        <pt></pt>
      </prop>
      <set num="DM23-RP2-8">DM23-RP2</set>
      <related></related>
      <tablerow>2</tablerow>
    </card>
    <card>
      <name>Perfect Mysticroar</name>
      <text>
■ If you have 4 or more cards in your mana zone that cost 7 or more, this spell costs 2 less to cast.
■ Choose 2 of the following. ''(You may choose the same one twice.)''
:► Draw 2 cards.
:► Choose one of your opponent's creatures and put it into it's owner's mana zone.
:► Shuffle your deck, then reveal the top card. If it's a creature, put it.
  </text>
      <prop>
        <maintype>Spell</maintype>
        <type></type>
        <manacost>8</manacost>
        <colors>Water/Nature</colors>
        <pt></pt>
      </prop>
      <set num="DM23-RP2- 13B">DM23-RP2</set>
      <related></related>
      <tablerow>2</tablerow>
    </card>
    <card>
      <name>Perfect Mysticroar</name>
      <text>
■ If you have 4 or more cards in your mana zone that cost 7 or more, this spell costs 2 less to cast.
■ Choose 2 of the following. ''(You may choose the same one twice.)''
:► Draw 2 cards.
:► Choose one of your opponent's creatures and put it into it's owner's mana zone.
:► Shuffle your deck, then reveal the top card. If it's a creature, put it.
  </text>
      <prop>
        <maintype>Spell</maintype>
        <type></type>
        <manacost>8</manacost>
        <colors>Water/Nature</colors>
        <pt></pt>
      </prop>
      <set num="DM23-RP2- 11A">DM23-RP2</set>
      <related></related>
      <tablerow>2</tablerow>
    </card>
    <card>
      <name>Umbrella %3D Isabella, Abyss Attack Parasol</name>
      <text>
■ Double Breaker
■ When you put this creature or whenever it attacks, choose one of the following.
:► Choose one of your opponent's elements and destroy it. Then you may put the same number of cards as that element's cost from the top of your deck into your graveyard.
:► You may shuffle 13 cards from your graveyard and put them on the bottom of your deck. If you do, your opponent chooses 13 cards from their hand and battle zone shuffles them, and puts them on the bottom of their deck.
  </text>
      <prop>
        <maintype>Creature</maintype>
        <type>Abyss Royale</type>
        <manacost>8</manacost>
        <colors>Darkness</colors>
        <pt>9000</pt>
      </prop>
      <set num="DM23-RP2-S4">DM23-RP2</set>
      <related></related>
      <tablerow>2</tablerow>
    </card>
    <card>
      <name>Umbrella %3D Isabella, Abyss Attack Parasol</name>
      <text>
■ Double Breaker
■ When you put this creature or whenever it attacks, choose one of the following.
:► Choose one of your opponent's elements and destroy it. Then you may put the same number of cards as that element's cost from the top of your deck into your graveyard.
:► You may shuffle 13 cards from your graveyard and put them on the bottom of your deck. If you do, your opponent chooses 13 cards from their hand and battle zone shuffles them, and puts them on the bottom of their deck.
  </text>
      <prop>
        <maintype>Creature</maintype>
        <type>Abyss Royale</type>
        <manacost>8</manacost>
        <colors>Darkness</colors>
        <pt>9000</pt>
      </prop>
      <set num="DM23-RP2- 6B">DM23-RP2</set>
      <related></related>
      <tablerow>2</tablerow>
    </card>
    <card>
      <name>Umbrella %3D Isabella, Abyss Attack Parasol</name>
      <text>
■ Double Breaker
■ When you put this creature or whenever it attacks, choose one of the following.
:► Choose one of your opponent's elements and destroy it. Then you may put the same number of cards as that element's cost from the top of your deck into your graveyard.
:► You may shuffle 13 cards from your graveyard and put them on the bottom of your deck. If you do, your opponent chooses 13 cards from their hand and battle zone shuffles them, and puts them on the bottom of their deck.
  </text>
      <prop>
        <maintype>Creature</maintype>
        <type>Abyss Royale</type>
        <manacost>8</manacost>
        <colors>Darkness</colors>
        <pt>9000</pt>
      </prop>
      <set num="DM23-RP2- 4A">DM23-RP2</set>
      <related></related>
      <tablerow>2</tablerow>
    </card>
    <card>
      <name>Ultrabowl Giant/Father Touchdown</name>
      <text>
■ Mach Fighter
■ Triple Breaker
■ Whenever this creature wins a battle, you may choose one of your opponent's shields and put it into its owner's mana zone.
■ Your opponent can't use non-creature cards that cost 5 or less.
=========================
■ Choose one of your opponent's creatures and put it into its owner's mana zone. Then you may put a creature that costs less than that creature from your mana zone.
  </text>
      <prop>
        <maintype>Twinpact</maintype>
        <type>Giant/Giant Skill</type>
        <manacost>8</manacost>
        <colors>Nature/Nature</colors>
        <pt>12000</pt>
      </prop>
      <set num="DM23-RP2-S7">DM23-RP2</set>
      <related></related>
      <tablerow>2</tablerow>
    </card>
    <card>
      <name>Ultrabowl Giant/Father Touchdown</name>
      <text>
■ Mach Fighter
■ Triple Breaker
■ Whenever this creature wins a battle, you may choose one of your opponent's shields and put it into its owner's mana zone.
■ Your opponent can't use non-creature cards that cost 5 or less.
=========================
■ Choose one of your opponent's creatures and put it into its owner's mana zone. Then you may put a creature that costs less than that creature from your mana zone.
  </text>
      <prop>
        <maintype>Twinpact</maintype>
        <type>Giant/Giant Skill</type>
        <manacost>8</manacost>
        <colors>Nature/Nature</colors>
        <pt>12000</pt>
      </prop>
      <set num="DM23-RP2- 9B">DM23-RP2</set>
      <related></related>
      <tablerow>2</tablerow>
    </card>
    <card>
      <name>Ultrabowl Giant/Father Touchdown</name>
      <text>
■ Mach Fighter
■ Triple Breaker
■ Whenever this creature wins a battle, you may choose one of your opponent's shields and put it into its owner's mana zone.
■ Your opponent can't use non-creature cards that cost 5 or less.
=========================
■ Choose one of your opponent's creatures and put it into its owner's mana zone. Then you may put a creature that costs less than that creature from your mana zone.
  </text>
      <prop>
        <maintype>Twinpact</maintype>
        <type>Giant/Giant Skill</type>
        <manacost>8</manacost>
        <colors>Nature/Nature</colors>
        <pt>12000</pt>
      </prop>
      <set num="DM23-RP2- 7A">DM23-RP2</set>
      <related></related>
      <tablerow>2</tablerow>
    </card>
    <card>
      <name>Shikisokuzekku, Holy Chaos Great Ninja</name>
      <text>
■ Blocker
■ Triple Breaker
■ Whenever this creature taps, you may put any number of Mecha Del Stella cards from your hand.
■ Whenever one of your Mecha attacks or blocks, you may shieldify the top card of your deck.
■ If you have 10 or more shields, your Mecha Win All Battles
  </text>
      <prop>
        <maintype>Creature</maintype>
        <type>Mecha Del Sol/Shinobi</type>
        <manacost>8</manacost>
        <colors>Light</colors>
        <pt>13000</pt>
      </prop>
      <set num="DM23-RP2-S1">DM23-RP2</set>
      <related></related>
      <tablerow>2</tablerow>
    </card>
    <card>
      <name>Shikisokuzekku, Holy Chaos Great Ninja</name>
      <text>
■ Blocker
■ Triple Breaker
■ Whenever this creature taps, you may put any number of Mecha Del Stella cards from your hand.
■ Whenever one of your Mecha attacks or blocks, you may shieldify the top card of your deck.
■ If you have 10 or more shields, your Mecha Win All Battles
  </text>
      <prop>
        <maintype>Creature</maintype>
        <type>Mecha Del Sol/Shinobi</type>
        <manacost>8</manacost>
        <colors>Light</colors>
        <pt>13000</pt>
      </prop>
      <set num="DM23-RP2- 3B">DM23-RP2</set>
      <related></related>
      <tablerow>2</tablerow>
    </card>
    <card>
      <name>Shikisokuzekku, Holy Chaos Great Ninja</name>
      <text>
■ Blocker
■ Triple Breaker
■ Whenever this creature taps, you may put any number of Mecha Del Stella cards from your hand.
■ Whenever one of your Mecha attacks or blocks, you may shieldify the top card of your deck.
■ If you have 10 or more shields, your Mecha Win All Battles
  </text>
      <prop>
        <maintype>Creature</maintype>
        <type>Mecha Del Sol/Shinobi</type>
        <manacost>8</manacost>
        <colors>Light</colors>
        <pt>13000</pt>
      </prop>
      <set num="DM23-RP2- 1A">DM23-RP2</set>
      <related></related>
      <tablerow>2</tablerow>
    </card>
    <card>
      <name>Mimosastar, Primachine/"Mechaming", Summon Light Spell</name>
      <text>
■ Blocker
■ Double Breaker
=========================
■ Look at the top 3 cards of your deck. You may reveal a Mecha from among them and add it to your hand. Then put the rest on the bottom of your deck in any order.
  </text>
      <prop>
        <maintype>Twinpact</maintype>
        <type>Mecha Del Stella/Mecha Del Tech</type>
        <manacost>5</manacost>
        <colors>Light/Light</colors>
        <pt>7500</pt>
      </prop>
      <set num="DM23-RP2-51">DM23-RP2</set>
      <related></related>
      <tablerow>2</tablerow>
    </card>
    <card>
      <name>Bolshack Galaward</name>
      <text>
■ This creature costs 1 less to summon for each creature in the battle zone. It can't cost 0 or less.
■ Speed Attacker
■ Double Breaker
■ When you put this creature or whenever it attacks, you may choose one of your opponent's creatures. This creature and that creature battle.
■ Whenever this creature wins a battle, you may draw a card.
  </text>
      <prop>
        <maintype>Creature</maintype>
        <type>Armored Dragon</type>
        <manacost>8</manacost>
        <colors>Fire</colors>
        <pt>9000</pt>
      </prop>
      <set num="DM23-RP2-S5">DM23-RP2</set>
      <related></related>
      <tablerow>2</tablerow>
    </card>
    <card>
      <name>Bolshack Galaward</name>
      <text>
■ This creature costs 1 less to summon for each creature in the battle zone. It can't cost 0 or less.
■ Speed Attacker
■ Double Breaker
■ When you put this creature or whenever it attacks, you may choose one of your opponent's creatures. This creature and that creature battle.
■ Whenever this creature wins a battle, you may draw a card.
  </text>
      <prop>
        <maintype>Creature</maintype>
        <type>Armored Dragon</type>
        <manacost>8</manacost>
        <colors>Fire</colors>
        <pt>9000</pt>
      </prop>
      <set num="DM23-RP2- 7B">DM23-RP2</set>
      <related></related>
      <tablerow>2</tablerow>
    </card>
    <card>
      <name>Bolshack Galaward</name>
      <text>
■ This creature costs 1 less to summon for each creature in the battle zone. It can't cost 0 or less.
■ Speed Attacker
■ Double Breaker
■ When you put this creature or whenever it attacks, you may choose one of your opponent's creatures. This creature and that creature battle.
■ Whenever this creature wins a battle, you may draw a card.
  </text>
      <prop>
        <maintype>Creature</maintype>
        <type>Armored Dragon</type>
        <manacost>8</manacost>
        <colors>Fire</colors>
        <pt>9000</pt>
      </prop>
      <set num="DM23-RP2- 5A">DM23-RP2</set>
      <related></related>
      <tablerow>2</tablerow>
    </card>
    <card>
      <name>The Mute, Doomsday</name>
      <text>
■ Shield Trigger Plus
■ Icon
■ When you put this creature, you may draw 2 cards. If you do, discard a card from your hand.
  </text>
      <prop>
        <maintype>Creature</maintype>
        <type>Magic Outrage MAX</type>
        <manacost>3</manacost>
        <colors>Water</colors>
        <pt>3000</pt>
      </prop>
      <set num="DM23-RP2-15">DM23-RP2</set>
      <related></related>
      <tablerow>2</tablerow>
    </card>
    <card>
      <name>The Mute, Doomsday</name>
      <text>
■ Shield Trigger Plus
■ Icon
■ When you put this creature, you may draw 2 cards. If you do, discard a card from your hand.
  </text>
      <prop>
        <maintype>Creature</maintype>
        <type>Magic Outrage MAX</type>
        <manacost>3</manacost>
        <colors>Water</colors>
        <pt>3000</pt>
      </prop>
      <set num="DM23-RP2- 15B">DM23-RP2</set>
      <related></related>
      <tablerow>2</tablerow>
    </card>
    <card>
      <name>The Mute, Doomsday</name>
      <text>
■ Shield Trigger Plus
■ Icon
■ When you put this creature, you may draw 2 cards. If you do, discard a card from your hand.
  </text>
      <prop>
        <maintype>Creature</maintype>
        <type>Magic Outrage MAX</type>
        <manacost>3</manacost>
        <colors>Water</colors>
        <pt>3000</pt>
      </prop>
      <set num="DM23-RP2- 13A">DM23-RP2</set>
      <related></related>
      <tablerow>2</tablerow>
    </card>
    <card>
      <name>Nearpin Mosquito</name>
      <text>
■ Shield Trigger Plus
■ Icon
■ When you put this creature, you may return a card from your mana zone to your hand.
■ This creature can't attack players.
  </text>
      <prop>
        <maintype>Creature</maintype>
        <type>Giant Insect</type>
        <manacost>3</manacost>
        <colors>Nature</colors>
        <pt>6000</pt>
      </prop>
      <set num="DM23-RP2-26">DM23-RP2</set>
      <related></related>
      <tablerow>2</tablerow>
    </card>
    <card>
      <name>Elnariku, Primachine</name>
      <text>
■ Blocker
■ This creature can't attack players.
■ At the end of each turn, if you put 2 or more cards into your shield zone this turn, Mecha Mechraid 8. Mechraid
  </text>
      <prop>
        <maintype>Creature</maintype>
        <type>Mecha Del Stella/Shinobi</type>
        <manacost>4</manacost>
        <colors>Light</colors>
        <pt>8000</pt>
      </prop>
      <set num="DM23-RP2-28">DM23-RP2</set>
      <related></related>
      <tablerow>2</tablerow>
    </card>
    <card>
      <name>Himecut, Song Dance Music Love/♪ Frog's Child, where can we meet? I want to say I love you</name>
      <text>
■ Friend Burst
■ During your opponent's turn, whenever your opponent draws a second or subsequent card in that turn, you may also draw a card.
=========================
■ Choose up to 2 of your opponent's elements and return them to their owner's hand.
  </text>
      <prop>
        <maintype>Twinpact</maintype>
        <type>Magic Mermaid/Magic Song</type>
        <manacost>2</manacost>
        <colors>Water/Water</colors>
        <pt>2000</pt>
      </prop>
      <set num="DM23-RP2-13">DM23-RP2</set>
      <related></related>
      <tablerow>2</tablerow>
    </card>
    <card>
      <name>Eternal Green Par Life, Eighteenth Dragon</name>
      <text>
■ Double Sympathy: Giant ''(When you summon this creature, you may pay 2 less for each of your Giant creatures. It can't cost 0 or less.)''
■ Mach Fighter
■ Double Breaker
■ Whenever one of your Giants attacks, you may draw a card.
■ Your Giants cost 2 less to use. They can't cost 0 or less.
■ At the start of your turn, if you have 18 or more creatures, Alternate Win
  </text>
      <prop>
        <maintype>Creature</maintype>
        <type>Giant Dragon</type>
        <manacost>10</manacost>
        <colors>Nature</colors>
        <pt>11000</pt>
      </prop>
      <set num="DM23-RP2-S8">DM23-RP2</set>
      <related></related>
      <tablerow>2</tablerow>
    </card>
    <card>
      <name>Eternal Green Par Life, Eighteenth Dragon</name>
      <text>
■ Double Sympathy: Giant ''(When you summon this creature, you may pay 2 less for each of your Giant creatures. It can't cost 0 or less.)''
■ Mach Fighter
■ Double Breaker
■ Whenever one of your Giants attacks, you may draw a card.
■ Your Giants cost 2 less to use. They can't cost 0 or less.
■ At the start of your turn, if you have 18 or more creatures, Alternate Win
  </text>
      <prop>
        <maintype>Creature</maintype>
        <type>Giant Dragon</type>
        <manacost>10</manacost>
        <colors>Nature</colors>
        <pt>11000</pt>
      </prop>
      <set num="DM23-RP2- 10B">DM23-RP2</set>
      <related></related>
      <tablerow>2</tablerow>
    </card>
    <card>
      <name>Eternal Green Par Life, Eighteenth Dragon</name>
      <text>
■ Double Sympathy: Giant ''(When you summon this creature, you may pay 2 less for each of your Giant creatures. It can't cost 0 or less.)''
■ Mach Fighter
■ Double Breaker
■ Whenever one of your Giants attacks, you may draw a card.
■ Your Giants cost 2 less to use. They can't cost 0 or less.
■ At the start of your turn, if you have 18 or more creatures, Alternate Win
  </text>
      <prop>
        <maintype>Creature</maintype>
        <type>Giant Dragon</type>
        <manacost>10</manacost>
        <colors>Nature</colors>
        <pt>11000</pt>
      </prop>
      <set num="DM23-RP2- 8A">DM23-RP2</set>
      <related></related>
      <tablerow>2</tablerow>
    </card>
    <card>
      <name>Troy, Holy Chaos Ninpo</name>
      <text>
■ You may return one of your Mecha or Shinobi to your hand. If you do, you may put a Mecha or Shinobi creature that costs 5 or less from your hand.
  </text>
      <prop>
        <maintype>Spell</maintype>
        <type>Mecha Del Tech/Shinobi</type>
        <manacost>4</manacost>
        <colors>Light</colors>
        <pt></pt>
      </prop>
      <set num="DM23-RP2-55">DM23-RP2</set>
      <related></related>
      <tablerow>2</tablerow>
    </card>
    <card>
      <name>Kl’avia Mondo</name>
      <text>
■ Justdiver
■ At the start of your turn, you may draw a card.
■ At the end of each turn, if you cast a spell and summoned a creature this turn, Magic Mechraid 8. Mechraid
  </text>
      <prop>
        <maintype>Creature</maintype>
        <type>Magic Command</type>
        <manacost>5</manacost>
        <colors>Water</colors>
        <pt>5000</pt>
      </prop>
      <set num="DM23-RP2-14">DM23-RP2</set>
      <related></related>
      <tablerow>2</tablerow>
    </card>
    <card>
      <name>Messh, Explosion String Music Love/♪ If You and I can Sympathize, Majimonju</name>
      <text>
■ Friend Burst
=========================
■ Draw 3 cards.
  </text>
      <prop>
        <maintype>Twinpact</maintype>
        <type>Magic Mermaid/Magic Song</type>
        <manacost>4</manacost>
        <colors>Water/Water</colors>
        <pt>3000</pt>
      </prop>
      <set num="DM23-RP2-57">DM23-RP2</set>
      <related></related>
      <tablerow>2</tablerow>
    </card>
    <card>
      <name>Ganma, Ninja Chain Holy Chaos</name>
      <text>
■ Whenever this creature attacks, you may shieldify the top card of your deck.
■ Once per turn, whenever you put a card into your shield zone, Mecha Mechraid 5. Mechraid
  </text>
      <prop>
        <maintype>Creature</maintype>
        <type>Mecha Del Stella/Shinobi</type>
        <manacost>3</manacost>
        <colors>Light</colors>
        <pt>2000</pt>
      </prop>
      <set num="DM23-RP2-12">DM23-RP2</set>
      <related></related>
      <tablerow>2</tablerow>
    </card>
    <card>
      <name>Ganma, Ninja Chain Holy Chaos</name>
      <text>
■ Whenever this creature attacks, you may shieldify the top card of your deck.
■ Once per turn, whenever you put a card into your shield zone, Mecha Mechraid 5. Mechraid
  </text>
      <prop>
        <maintype>Creature</maintype>
        <type>Mecha Del Stella/Shinobi</type>
        <manacost>3</manacost>
        <colors>Light</colors>
        <pt>2000</pt>
      </prop>
      <set num="DM23-RP2- 14B">DM23-RP2</set>
      <related></related>
      <tablerow>2</tablerow>
    </card>
    <card>
      <name>Ganma, Ninja Chain Holy Chaos</name>
      <text>
■ Whenever this creature attacks, you may shieldify the top card of your deck.
■ Once per turn, whenever you put a card into your shield zone, Mecha Mechraid 5. Mechraid
  </text>
      <prop>
        <maintype>Creature</maintype>
        <type>Mecha Del Stella/Shinobi</type>
        <manacost>3</manacost>
        <colors>Light</colors>
        <pt>2000</pt>
      </prop>
      <set num="DM23-RP2- 12A">DM23-RP2</set>
      <related></related>
      <tablerow>2</tablerow>
    </card>
    <card>
      <name>The Showtime</name>
      <text>
■ Shield Trigger
■ Choose one of your opponent's elements that costs 4 or less and put it on the bottom of its owner's deck.
  </text>
      <prop>
        <maintype>Spell</maintype>
        <type>Invitation to the Abyss</type>
        <manacost>3</manacost>
        <colors>Darkness</colors>
        <pt></pt>
      </prop>
      <set num="DM23-RP2-39">DM23-RP2</set>
      <related></related>
      <tablerow>2</tablerow>
    </card>
    <card>
      <name>Kl'avia Tune</name>
      <text>
■ Blocker
■ Triple Breaker
■ When you put this creature, until the start of your next turn, your opponent's creatures that cost 7 or less can't attack or block.
■ Your opponent's non-creature cards that cost 7 or less cost 8 instead.
■ Your opponent Unchoosable
  </text>
      <prop>
        <maintype>Creature</maintype>
        <type>Magic Command Dragon</type>
        <manacost>8</manacost>
        <colors>Water</colors>
        <pt>12000</pt>
      </prop>
      <set num="DM23-RP2-S3">DM23-RP2</set>
      <related></related>
      <tablerow>2</tablerow>
    </card>
    <card>
      <name>Kl'avia Tune</name>
      <text>
■ Blocker
■ Triple Breaker
■ When you put this creature, until the start of your next turn, your opponent's creatures that cost 7 or less can't attack or block.
■ Your opponent's non-creature cards that cost 7 or less cost 8 instead.
■ Your opponent Unchoosable
  </text>
      <prop>
        <maintype>Creature</maintype>
        <type>Magic Command Dragon</type>
        <manacost>8</manacost>
        <colors>Water</colors>
        <pt>12000</pt>
      </prop>
      <set num="DM23-RP2- 5B">DM23-RP2</set>
      <related></related>
      <tablerow>2</tablerow>
    </card>
    <card>
      <name>Kl'avia Tune</name>
      <text>
■ Blocker
■ Triple Breaker
■ When you put this creature, until the start of your next turn, your opponent's creatures that cost 7 or less can't attack or block.
■ Your opponent's non-creature cards that cost 7 or less cost 8 instead.
■ Your opponent Unchoosable
  </text>
      <prop>
        <maintype>Creature</maintype>
        <type>Magic Command Dragon</type>
        <manacost>8</manacost>
        <colors>Water</colors>
        <pt>12000</pt>
      </prop>
      <set num="DM23-RP2- 3A">DM23-RP2</set>
      <related></related>
      <tablerow>2</tablerow>
    </card>
    <card>
      <name>Bleach, Music Love Band</name>
      <text>
■ Whenever this creature attacks, choose one of your opponent's creatures. That creature can't attack or block until the start of your next turn.
■ Whenever this creature untaps, the next spell you cast this turn costs up to 3 less. ''(It can't cost 0 or less.)''
  </text>
      <prop>
        <maintype>Creature</maintype>
        <type>Magic Mermaid</type>
        <manacost>2</manacost>
        <colors>Water</colors>
        <pt>2000</pt>
      </prop>
      <set num="DM23-RP2-35">DM23-RP2</set>
      <related></related>
      <tablerow>2</tablerow>
    </card>
    <card>
      <name>Cerulean Axe Dragon/Doubleaxe Charger</name>
      <text>
■ Double Breaker
■ When you put this creature, you may choose one of your opponent's creatures. This creature and that creature battle.
=========================
■ Put up to 2 cards from your hand on the bottom of your deck in any order, then draw the same number of cards.
■ Charger
  </text>
      <prop>
        <maintype>Twinpact</maintype>
        <type>Armored Dragon/Armored Arts</type>
        <manacost>7</manacost>
        <colors>Fire/Fire</colors>
        <pt>9000</pt>
      </prop>
      <set num="DM23-RP2-40">DM23-RP2</set>
      <related></related>
      <tablerow>2</tablerow>
    </card>
    <card>
      <name>Balupialesk, Thunderflame Soaring Armor</name>
      <text>
■ Speed Attacker
■ This creature can't be destroyed while battling.
■ Whenever this creature attacks, you may put a Fire Bird from your hand.
■ After this creature attacks, you may destroy 5 of your Fire Birds. If you do, take an extra turn after this one.
  </text>
      <prop>
        <maintype>Creature</maintype>
        <type>Armored Fire Bird/Armored Wyvern</type>
        <manacost>5</manacost>
        <colors>Fire</colors>
        <pt>5000</pt>
      </prop>
      <set num="DM23-RP2-S6">DM23-RP2</set>
      <related></related>
      <tablerow>2</tablerow>
    </card>
    <card>
      <name>Balupialesk, Thunderflame Soaring Armor</name>
      <text>
■ Speed Attacker
■ This creature can't be destroyed while battling.
■ Whenever this creature attacks, you may put a Fire Bird from your hand.
■ After this creature attacks, you may destroy 5 of your Fire Birds. If you do, take an extra turn after this one.
  </text>
      <prop>
        <maintype>Creature</maintype>
        <type>Armored Fire Bird/Armored Wyvern</type>
        <manacost>5</manacost>
        <colors>Fire</colors>
        <pt>5000</pt>
      </prop>
      <set num="DM23-RP2- 8B">DM23-RP2</set>
      <related></related>
      <tablerow>2</tablerow>
    </card>
    <card>
      <name>Balupialesk, Thunderflame Soaring Armor</name>
      <text>
■ Speed Attacker
■ This creature can't be destroyed while battling.
■ Whenever this creature attacks, you may put a Fire Bird from your hand.
■ After this creature attacks, you may destroy 5 of your Fire Birds. If you do, take an extra turn after this one.
  </text>
      <prop>
        <maintype>Creature</maintype>
        <type>Armored Fire Bird/Armored Wyvern</type>
        <manacost>5</manacost>
        <colors>Fire</colors>
        <pt>5000</pt>
      </prop>
      <set num="DM23-RP2- 6A">DM23-RP2</set>
      <related></related>
      <tablerow>2</tablerow>
    </card>
    <card>
      <name>Kagi, Ninja Claw Holy Chaos</name>
      <text>
■ Shield Trigger Plus
■ Icon
■ Blocker
■ Your hand can't be discarded by your opponent's spells or creature ability
  </text>
      <prop>
        <maintype>Creature</maintype>
        <type>Mecha Del Stella/Shinobi</type>
        <manacost>3</manacost>
        <colors>Light</colors>
        <pt>3500</pt>
      </prop>
      <set num="DM23-RP2-29">DM23-RP2</set>
      <related></related>
      <tablerow>2</tablerow>
    </card>
    <card>
      <name>Shirley C, Holy Chaos Ninja/Shirley Charger</name>
      <text>
■ Double Breaker
■ When you put this creature, shieldify the top 2 cards of your deck.
=========================
■ Shieldify the top card of your deck.
■ Charger
  </text>
      <prop>
        <maintype>Twinpact</maintype>
        <type>Mecha Del Stella/Shinobi/Mecha Del Tech</type>
        <manacost>7</manacost>
        <colors>Light/Light</colors>
        <pt>8500</pt>
      </prop>
      <set num="DM23-RP2-27">DM23-RP2</set>
      <related></related>
      <tablerow>2</tablerow>
    </card>
    <card>
      <name>Shirley C, Holy Chaos Ninja/Shirley Charger</name>
      <text>
■ Double Breaker
■ When you put this creature, shieldify the top 2 cards of your deck.
=========================
■ Shieldify the top card of your deck.
■ Charger
  </text>
      <prop>
        <maintype>Twinpact</maintype>
        <type>Mecha Del Stella/Shinobi/Mecha Del Tech</type>
        <manacost>7</manacost>
        <colors>Light/Light</colors>
        <pt>8500</pt>
      </prop>
      <set num="DM23-RP2- 17B">DM23-RP2</set>
      <related></related>
      <tablerow>2</tablerow>
    </card>
    <card>
      <name>Shirley C, Holy Chaos Ninja/Shirley Charger</name>
      <text>
■ Double Breaker
■ When you put this creature, shieldify the top 2 cards of your deck.
=========================
■ Shieldify the top card of your deck.
■ Charger
  </text>
      <prop>
        <maintype>Twinpact</maintype>
        <type>Mecha Del Stella/Shinobi/Mecha Del Tech</type>
        <manacost>7</manacost>
        <colors>Light/Light</colors>
        <pt>8500</pt>
      </prop>
      <set num="DM23-RP2- 15A">DM23-RP2</set>
      <related></related>
      <tablerow>2</tablerow>
    </card>
    <card>
      <name>Energico, Phoneme Symbol B Minor/♪ From the Surface, To Catch the Sky Charger</name>
      <text>
■ Double Breaker
■ When you put this creature, draw 2 cards.
=========================
■ Draw a card, then discard a card from your hand.
■ Charger
  </text>
      <prop>
        <maintype>Twinpact</maintype>
        <type>Magic Crystal Command Dragon/Magic Song</type>
        <manacost>7</manacost>
        <colors>Water/Water</colors>
        <pt>9000</pt>
      </prop>
      <set num="DM23-RP2-31">DM23-RP2</set>
      <related></related>
      <tablerow>2</tablerow>
    </card>
    <card>
      <name>Energico, Phoneme Symbol B Minor/♪ From the Surface, To Catch the Sky Charger</name>
      <text>
■ Double Breaker
■ When you put this creature, draw 2 cards.
=========================
■ Draw a card, then discard a card from your hand.
■ Charger
  </text>
      <prop>
        <maintype>Twinpact</maintype>
        <type>Magic Crystal Command Dragon/Magic Song</type>
        <manacost>7</manacost>
        <colors>Water/Water</colors>
        <pt>9000</pt>
      </prop>
      <set num="DM23-RP2- 18B">DM23-RP2</set>
      <related></related>
      <tablerow>2</tablerow>
    </card>
    <card>
      <name>Energico, Phoneme Symbol B Minor/♪ From the Surface, To Catch the Sky Charger</name>
      <text>
■ Double Breaker
■ When you put this creature, draw 2 cards.
=========================
■ Draw a card, then discard a card from your hand.
■ Charger
  </text>
      <prop>
        <maintype>Twinpact</maintype>
        <type>Magic Crystal Command Dragon/Magic Song</type>
        <manacost>7</manacost>
        <colors>Water/Water</colors>
        <pt>9000</pt>
      </prop>
      <set num="DM23-RP2- 16A">DM23-RP2</set>
      <related></related>
      <tablerow>2</tablerow>
    </card>
    <card>
      <name>Monocle %3D Doctorle/"It's the eye that sees through everything."</name>
      <text>
■ Double Breaker
■ When you put this creature, choose one of your opponent's creatures and destroy it.
=========================
■ Each player puts the top 2 cards of their deck into their graveyard.
■ Charger
  </text>
      <prop>
        <maintype>Twinpact</maintype>
        <type>Abyss Royale/Invitation to the Abyss</type>
        <manacost>7</manacost>
        <colors>Darkness/Darkness</colors>
        <pt>8000</pt>
      </prop>
      <set num="DM23-RP2-36">DM23-RP2</set>
      <related></related>
      <tablerow>2</tablerow>
    </card>
    <card>
      <name>Friend Giant/Takeback Charger</name>
      <text>
■ Double Breaker
■ When you put this creature, put the top 2 cards of your deck into your mana zone tapped.
=========================
■ You may choose an element that costs 3 or less and put it into its owner's mana zone tapped.
■ Charger
  </text>
      <prop>
        <maintype>Twinpact</maintype>
        <type>Giant/Giant Skill</type>
        <manacost>7</manacost>
        <colors>Nature/Nature</colors>
        <pt>11000</pt>
      </prop>
      <set num="DM23-RP2-45">DM23-RP2</set>
      <related></related>
      <tablerow>2</tablerow>
    </card>
    <card>
      <name>Bolshack Koya Dragon</name>
      <text>
■ Shield Trigger Plus
■ Icon
■ Speed Attacker
  </text>
      <prop>
        <maintype>Creature</maintype>
        <type>Armored Dragon</type>
        <manacost>4</manacost>
        <colors>Fire</colors>
        <pt>4000</pt>
      </prop>
      <set num="DM23-RP2-41">DM23-RP2</set>
      <related></related>
      <tablerow>2</tablerow>
    </card>
    <card>
      <name>Encounter with the Sun</name>
      <text>
■ Armored Mechraid 5. Mechraid
■ Each of your creatures gets "speed attacker". ''(A creature that has "speed attacker doesn't get summoning sickness.)''
  </text>
      <prop>
        <maintype>Spell</maintype>
        <type>Armored Arts</type>
        <manacost>5</manacost>
        <colors>Fire</colors>
        <pt></pt>
      </prop>
      <set num="DM23-RP2-70">DM23-RP2</set>
      <related></related>
      <tablerow>2</tablerow>
    </card>
    <card>
      <name>Magic Haiku Collector/♪ Magison, Collect Up Fastly, Stream</name>
      <text>
■ Justdiver
■ Double Breaker
■ Each of your twinpact cards in your hand gets "Strike Back: Twinpact".
=========================
■ Look at the top 3 cards of your deck. Choose any number of twinpact cards from among them, reveal them to your opponent and add them to your hand. Put the rest on on the bottom of your deck in any order.
  </text>
      <prop>
        <maintype>Twinpact</maintype>
        <type>Magic Cyber Command/Magic Song</type>
        <manacost>5</manacost>
        <colors>Water/Water</colors>
        <pt>6000</pt>
      </prop>
      <set num="DM23-RP2-S2">DM23-RP2</set>
      <related></related>
      <tablerow>2</tablerow>
    </card>
    <card>
      <name>Magic Haiku Collector/♪ Magison, Collect Up Fastly, Stream</name>
      <text>
■ Justdiver
■ Double Breaker
■ Each of your twinpact cards in your hand gets "Strike Back: Twinpact".
=========================
■ Look at the top 3 cards of your deck. Choose any number of twinpact cards from among them, reveal them to your opponent and add them to your hand. Put the rest on on the bottom of your deck in any order.
  </text>
      <prop>
        <maintype>Twinpact</maintype>
        <type>Magic Cyber Command/Magic Song</type>
        <manacost>5</manacost>
        <colors>Water/Water</colors>
        <pt>6000</pt>
      </prop>
      <set num="DM23-RP2- 4B">DM23-RP2</set>
      <related></related>
      <tablerow>2</tablerow>
    </card>
    <card>
      <name>Magic Haiku Collector/♪ Magison, Collect Up Fastly, Stream</name>
      <text>
■ Justdiver
■ Double Breaker
■ Each of your twinpact cards in your hand gets "Strike Back: Twinpact".
=========================
■ Look at the top 3 cards of your deck. Choose any number of twinpact cards from among them, reveal them to your opponent and add them to your hand. Put the rest on on the bottom of your deck in any order.
  </text>
      <prop>
        <maintype>Twinpact</maintype>
        <type>Magic Cyber Command/Magic Song</type>
        <manacost>5</manacost>
        <colors>Water/Water</colors>
        <pt>6000</pt>
      </prop>
      <set num="DM23-RP2- 2A">DM23-RP2</set>
      <related></related>
      <tablerow>2</tablerow>
    </card>
    <card>
      <name>Aqua Vibrato</name>
      <text>
■ When you put this creature, draw a card.
  </text>
      <prop>
        <maintype>Creature</maintype>
        <type>Magic Liquid People</type>
        <manacost>2</manacost>
        <colors>Water</colors>
        <pt>1000</pt>
      </prop>
      <set num="DM23-RP2-59">DM23-RP2</set>
      <related></related>
      <tablerow>2</tablerow>
    </card>
    <card>
      <name>Daidai, Marching Baton</name>
      <text>
■ Shield Trigger Plus
■ Icon
■ You may summon this creature from your mana zone.
  </text>
      <prop>
        <maintype>Creature</maintype>
        <type>Giant Snow Faerie</type>
        <manacost>2</manacost>
        <colors>Nature</colors>
        <pt>3000</pt>
      </prop>
      <set num="DM23-RP2-48">DM23-RP2</set>
      <related></related>
      <tablerow>2</tablerow>
    </card>
    <card>
      <name>Midori, Marching Drum/Hamelin Harmony</name>
      <text>
■ When you put this creature, look at the top 2 cards of your deck. Put one of them into your mana zone.
=========================
■ Put all creatures into their owner's mana zone tapped.
  </text>
      <prop>
        <maintype>Twinpact</maintype>
        <type>Giant Snow Faerie/Giant Skill</type>
        <manacost>3</manacost>
        <colors>Nature/Nature</colors>
        <pt>3000</pt>
      </prop>
      <set num="DM23-RP2-24">DM23-RP2</set>
      <related></related>
      <tablerow>2</tablerow>
    </card>
    <card>
      <name>Bolshack Sky, Armored Wheel Double Flight</name>
      <text>
■ Speed Attacker
■ Blocker
■ Whenever another creature untaps, untap this creature.
  </text>
      <prop>
        <maintype>Creature</maintype>
        <type>Armored Dragon/Mecha Del Dinero</type>
        <manacost>5</manacost>
        <colors>Light/Fire</colors>
        <pt>5500</pt>
      </prop>
      <set num="DM23-RP2-50">DM23-RP2</set>
      <related></related>
      <tablerow>2</tablerow>
    </card>
    <card>
      <name>Bolshack Sky, Armored Wheel Double Flight</name>
      <text>
■ Speed Attacker
■ Blocker
■ Whenever another creature untaps, untap this creature.
  </text>
      <prop>
        <maintype>Creature</maintype>
        <type>Armored Dragon/Mecha Del Dinero</type>
        <manacost>5</manacost>
        <colors>Light/Fire</colors>
        <pt>5500</pt>
      </prop>
      <set num="DM23-RP2- 19B">DM23-RP2</set>
      <related></related>
      <tablerow>2</tablerow>
    </card>
    <card>
      <name>Bolshack Sky, Armored Wheel Double Flight</name>
      <text>
■ Speed Attacker
■ Blocker
■ Whenever another creature untaps, untap this creature.
  </text>
      <prop>
        <maintype>Creature</maintype>
        <type>Armored Dragon/Mecha Del Dinero</type>
        <manacost>5</manacost>
        <colors>Light/Fire</colors>
        <pt>5500</pt>
      </prop>
      <set num="DM23-RP2- 17A">DM23-RP2</set>
      <related></related>
      <tablerow>2</tablerow>
    </card>
    <card>
      <name>Reaper XENARCH Hand</name>
      <text>
■ Shield Trigger Plus
■ Choose one of your opponent's creatures and destroy it.
■ Icon
  </text>
      <prop>
        <maintype>Spell</maintype>
        <type></type>
        <manacost>6</manacost>
        <colors>Darkness</colors>
        <pt></pt>
      </prop>
      <set num="DM23-RP2-19">DM23-RP2</set>
      <related></related>
      <tablerow>2</tablerow>
    </card>
    <card>
      <name>Flavum Gorghini</name>
      <text>
■ If you have 2 or more creatures that have "blocker", this creature costs 3 less to summon.
■ Double Breaker
■ When you summon this creature, Mechraid
■ Untap all your Mecha End Step
  </text>
      <prop>
        <maintype>Creature</maintype>
        <type>Mecha Del Dinero/Supercar Dragon</type>
        <manacost>9</manacost>
        <colors>Light</colors>
        <pt>11500</pt>
      </prop>
      <set num="DM23-RP2-1">DM23-RP2</set>
      <related></related>
      <tablerow>2</tablerow>
    </card>
    <card>
      <name>Flavum Gorghini</name>
      <text>
■ If you have 2 or more creatures that have "blocker", this creature costs 3 less to summon.
■ Double Breaker
■ When you summon this creature, Mechraid
■ Untap all your Mecha End Step
  </text>
      <prop>
        <maintype>Creature</maintype>
        <type>Mecha Del Dinero/Supercar Dragon</type>
        <manacost>9</manacost>
        <colors>Light</colors>
        <pt>11500</pt>
      </prop>
      <set num="DM23-RP2- 11B">DM23-RP2</set>
      <related></related>
      <tablerow>2</tablerow>
    </card>
    <card>
      <name>Flavum Gorghini</name>
      <text>
■ If you have 2 or more creatures that have "blocker", this creature costs 3 less to summon.
■ Double Breaker
■ When you summon this creature, Mechraid
■ Untap all your Mecha End Step
  </text>
      <prop>
        <maintype>Creature</maintype>
        <type>Mecha Del Dinero/Supercar Dragon</type>
        <manacost>9</manacost>
        <colors>Light</colors>
        <pt>11500</pt>
      </prop>
      <set num="DM23-RP2- 9A">DM23-RP2</set>
      <related></related>
      <tablerow>2</tablerow>
    </card>
    <card>
      <name>Go! Ink Steady</name>
      <text>
■ If you have 2 or more twinpact creatures, this creature costs 3 less to summon.
■ Double Breaker
■ When you summon this creature, Mechraid
■ Your Magic creatures can't be attacked or blocked.
  </text>
      <prop>
        <maintype>Creature</maintype>
        <type>Magic Poseidia Dragon</type>
        <manacost>9</manacost>
        <colors>Water</colors>
        <pt>11000</pt>
      </prop>
      <set num="DM23-RP2-3">DM23-RP2</set>
      <related></related>
      <tablerow>2</tablerow>
    </card>
    <card>
      <name>Rate:Ga:Fuyoki</name>
      <text>
■ When you summon this creature, you may destroy 2 of your creatures. If you do, this creature costs 3 less to summon.
■ Double Breaker
■ When you summon this creature, Mechraid
■ Each of your Abyss get "slayer".
  </text>
      <prop>
        <maintype>Creature</maintype>
        <type>Noir Abyss</type>
        <manacost>9</manacost>
        <colors>Darkness</colors>
        <pt>11000</pt>
      </prop>
      <set num="DM23-RP2-4">DM23-RP2</set>
      <related></related>
      <tablerow>2</tablerow>
    </card>
    <card>
      <name>Bolshack Noblesse Dragon</name>
      <text>
■ If you have 3 or more fire elements, this creature costs 3 less to summon.
■ Double Breaker
■ When you summon this creature, Mechraid
■ Each of your Armored get +3000 power while battling.
  </text>
      <prop>
        <maintype>Creature</maintype>
        <type>Armored Dragon</type>
        <manacost>9</manacost>
        <colors>Fire</colors>
        <pt>10000+</pt>
      </prop>
      <set num="DM23-RP2-6">DM23-RP2</set>
      <related></related>
      <tablerow>2</tablerow>
    </card>
    <card>
      <name>Ranshin! Albatross Tarantula</name>
      <text>
■ If you have 2 or more creatures that have power 6000 or more, this creature costs 3 less to summon.
■ Triple Breaker
■ When you summon this creature, Mechraid
■ Whenever one of your Giants would be destroyed, you may put them into your mana zone instead.
  </text>
      <prop>
        <maintype>Creature</maintype>
        <type>Giant Insect</type>
        <manacost>9</manacost>
        <colors>Nature</colors>
        <pt>13000</pt>
      </prop>
      <set num="DM23-RP2-7">DM23-RP2</set>
      <related></related>
      <tablerow>2</tablerow>
    </card>
    <card>
      <name>Fantasista Life</name>
      <text>
■ Put the top 2 cards of your deck into your mana zone tapped, then return a card from your mana zone to your hand.
  </text>
      <prop>
        <maintype>Spell</maintype>
        <type>Giant Skill</type>
        <manacost>4</manacost>
        <colors>Nature</colors>
        <pt></pt>
      </prop>
      <set num="DM23-RP2-74">DM23-RP2</set>
      <related></related>
      <tablerow>2</tablerow>
    </card>
    <card>
      <name>Fantasista Life</name>
      <text>
■ Put the top 2 cards of your deck into your mana zone tapped, then return a card from your mana zone to your hand.
  </text>
      <prop>
        <maintype>Spell</maintype>
        <type>Giant Skill</type>
        <manacost>4</manacost>
        <colors>Nature</colors>
        <pt></pt>
      </prop>
      <set num="DM23-RP2- 22B">DM23-RP2</set>
      <related></related>
      <tablerow>2</tablerow>
    </card>
    <card>
      <name>Fantasista Life</name>
      <text>
■ Put the top 2 cards of your deck into your mana zone tapped, then return a card from your mana zone to your hand.
  </text>
      <prop>
        <maintype>Spell</maintype>
        <type>Giant Skill</type>
        <manacost>4</manacost>
        <colors>Nature</colors>
        <pt></pt>
      </prop>
      <set num="DM23-RP2- 20A">DM23-RP2</set>
      <related></related>
      <tablerow>2</tablerow>
    </card>
    <card>
      <name>Cyan, Marching Bell/Mimiru Musical</name>
      <text>
■ Friend Burst
■ Whenever this creature wins a battle, draw a card and break one of your opponent's shields.
■ Guardman
=========================
■ One of your creatures gets +4000 power until the End Step
  </text>
      <prop>
        <maintype>Twinpact</maintype>
        <type>Giant Snow Faerie/Giant Skill</type>
        <manacost>5</manacost>
        <colors>Nature/Nature</colors>
        <pt>7000</pt>
      </prop>
      <set num="DM23-RP2-23">DM23-RP2</set>
      <related></related>
      <tablerow>2</tablerow>
    </card>
    <card>
      <name>Mintojuba, Primachine/Minteor Ringing</name>
      <text>
■ Blocker
■ Double Breaker
■ Friend Burst
=========================
■ Choose one of the following for each of your creatures.
:► Choose one of your opponent's creatures and tap it.
:► Draw a card.
  </text>
      <prop>
        <maintype>Twinpact</maintype>
        <type>Mecha Del Stella/Mecha Del Tech</type>
        <manacost>6</manacost>
        <colors>Light/Light</colors>
        <pt>8000</pt>
      </prop>
      <set num="DM23-RP2-9">DM23-RP2</set>
      <related></related>
      <tablerow>2</tablerow>
    </card>
    <card>
      <name>Aururi-T8</name>
      <text>
■ Blocker
■ Double Breaker
■ True Escape ''(When this creature would leave, you may add 2 of your shields to your hand instead. You can't use the "shield trigger" abilities of those shields.)
■ If you have no shields, this creature can't leave.
  </text>
      <prop>
        <maintype>Creature</maintype>
        <type>Mecha Del Dinero</type>
        <manacost>5</manacost>
        <colors>Light</colors>
        <pt>6000</pt>
      </prop>
      <set num="DM23-RP2-10">DM23-RP2</set>
      <related></related>
      <tablerow>2</tablerow>
    </card>
    <card>
      <name>Yobirin %3D Ririn/"...who do you want to call?"</name>
      <text>
■ Friend Burst
■ Whenever another creature is destroyed, draw a card.
=========================
■ Choose one of your opponent's creatures. That creature gets -6000 power until the End Step
  </text>
      <prop>
        <maintype>Twinpact</maintype>
        <type>Abyss Royale/Invitation to the Abyss</type>
        <manacost>5</manacost>
        <colors>Darkness/Darkness</colors>
        <pt>4000</pt>
      </prop>
      <set num="DM23-RP2-16">DM23-RP2</set>
      <related></related>
      <tablerow>2</tablerow>
    </card>
    <card>
      <name>Make Jam</name>
      <text>
■ Put the top 3 cards of your deck into your graveyard.
■ Put all creatures from your graveyard that cost the same as or less than the number of cards in your mana zone into the battle zone tapped. When those creatures are put and their ability
  </text>
      <prop>
        <maintype>Spell</maintype>
        <type>Invitation to the Abyss</type>
        <manacost>9</manacost>
        <colors>Darkness</colors>
        <pt></pt>
      </prop>
      <set num="DM23-RP2-18">DM23-RP2</set>
      <related></related>
      <tablerow>2</tablerow>
    </card>
    <card>
      <name>Vertical Wyvern</name>
      <text>
■ Shield Trigger Plus
■ Icon
■ When you put this creature, until the start of your next turn, whenever you are attacked, your opponent chooses one of their creatures that has the lowest power and destroys it.
  </text>
      <prop>
        <maintype>Creature</maintype>
        <type>Armored Wyvern</type>
        <manacost>6</manacost>
        <colors>Fire</colors>
        <pt>5000</pt>
      </prop>
      <set num="DM23-RP2-21">DM23-RP2</set>
      <related></related>
      <tablerow>2</tablerow>
    </card>
    <card>
      <name>Karakara Warn Lupia/"Leave this to meppi!"</name>
      <text>
■ Friend Burst
■ Each of your other Fire Birds gets +2000 power.
=========================
■ Discard a card from your hand, then draw 2 cards.
  </text>
      <prop>
        <maintype>Twinpact</maintype>
        <type>Armored Fire Bird/Armored Arts</type>
        <manacost>2</manacost>
        <colors>Fire/Fire</colors>
        <pt>2000</pt>
      </prop>
      <set num="DM23-RP2-20">DM23-RP2</set>
      <related></related>
      <tablerow>2</tablerow>
    </card>
    <card>
      <name>Parrotta Night Mieppi</name>
      <text>
■ Whenever you put a Dragon, draw a card.
■ If you have a tapped Dragon creature, your Fire Birds can't be attacked.
  </text>
      <prop>
        <maintype>Creature</maintype>
        <type>Armored Fire Bird</type>
        <manacost>3</manacost>
        <colors>Fire</colors>
        <pt>4000</pt>
      </prop>
      <set num="DM23-RP2-22">DM23-RP2</set>
      <related></related>
      <tablerow>2</tablerow>
    </card>
    <card>
      <name>Fullcourse Giant</name>
      <text>
■ Mach Fighter
■ Double Breaker
■ Whenever this creature would destroy one of your opponent's creatures while battling, you may Giant Mechraid 8 instead. Mechraid
  </text>
      <prop>
        <maintype>Creature</maintype>
        <type>Giant</type>
        <manacost>6</manacost>
        <colors>Nature</colors>
        <pt>9000</pt>
      </prop>
      <set num="DM23-RP2-25">DM23-RP2</set>
      <related></related>
      <tablerow>2</tablerow>
    </card>
    <card>
      <name>Regomiele, Primachine</name>
      <text>
■ When you put this creature, choose one of your opponent's creatures and tap it. While this creature is in the battle zone, that creature doesn't untap.
  </text>
      <prop>
        <maintype>Creature</maintype>
        <type>Mecha Del Stella</type>
        <manacost>3</manacost>
        <colors>Light</colors>
        <pt>3000</pt>
      </prop>
      <set num="DM23-RP2-30">DM23-RP2</set>
      <related></related>
      <tablerow>2</tablerow>
    </card>
    <card>
      <name>Idol Fish/♪ A Big Sky, Moonsault, Little Bit Slanting</name>
      <text>
■ At the start of your turn, you may return this creature to your hand. If you do, Magic Mechraid 5. Mechraid
=========================
■ Shield Trigger
■ Your opponent chooses 2 of their untapped creatures and returns them to their owner's hand.
  </text>
      <prop>
        <maintype>Twinpact</maintype>
        <type>Magic Fish/Magic Song</type>
        <manacost>3</manacost>
        <colors>Water/Water</colors>
        <pt>4000</pt>
      </prop>
      <set num="DM23-RP2-32">DM23-RP2</set>
      <related></related>
      <tablerow>2</tablerow>
    </card>
    <card>
      <name>Zentsu</name>
      <text>
■ Once per turn, whenever your opponent puts an element for no cost, you may Magic Mechraid 5. Mechraid
  </text>
      <prop>
        <maintype>Creature</maintype>
        <type>Magic Cyber Lord</type>
        <manacost>3</manacost>
        <colors>Water</colors>
        <pt>3000</pt>
      </prop>
      <set num="DM23-RP2-33">DM23-RP2</set>
      <related></related>
      <tablerow>2</tablerow>
    </card>
    <card>
      <name>Takasugi Wawonchopper</name>
      <text>
■ Shield Trigger Plus
■ Icon
■ This creature can't be blocked.
  </text>
      <prop>
        <maintype>Creature</maintype>
        <type>Magic Merfolk</type>
        <manacost>2</manacost>
        <colors>Water</colors>
        <pt>3000</pt>
      </prop>
      <set num="DM23-RP2-34">DM23-RP2</set>
      <related></related>
      <tablerow>2</tablerow>
    </card>
    <card>
      <name>Carpet %3D Garpet/"Hmm, lets take your wishes into consideration."</name>
      <text>
■ Abyss Rush
■ Whenever your opponent casts a spell, your opponent chooses 2 cards from their hand and discards them.
=========================
■ Put the top 2 cards of your deck into your graveyard. If the 2 cards put this way are both Abyss, you may return an Abyss from your graveyard to your hand.
  </text>
      <prop>
        <maintype>Twinpact</maintype>
        <type>Abyss Royale/Invitation to the Abyss</type>
        <manacost>4</manacost>
        <colors>Darkness/Darkness</colors>
        <pt>4000</pt>
      </prop>
      <set num="DM23-RP2-37">DM23-RP2</set>
      <related></related>
      <tablerow>2</tablerow>
    </card>
    <card>
      <name>Do:Toyakki</name>
      <text>
■ Shield Trigger Plus
■ Icon
■ Slayer
  </text>
      <prop>
        <maintype>Creature</maintype>
        <type>Noir Abyss</type>
        <manacost>3</manacost>
        <colors>Darkness</colors>
        <pt>1000</pt>
      </prop>
      <set num="DM23-RP2-38">DM23-RP2</set>
      <related></related>
      <tablerow>2</tablerow>
    </card>
    <card>
      <name>Little Jet Balupia</name>
      <text>
■ Whenever one of your creatures attacks, if it's the second attack of your turn, Armored Mechraid 5. Mechraid
  </text>
      <prop>
        <maintype>Creature</maintype>
        <type>Armored Fire Bird</type>
        <manacost>3</manacost>
        <colors>Fire</colors>
        <pt>3000</pt>
      </prop>
      <set num="DM23-RP2-42">DM23-RP2</set>
      <related></related>
      <tablerow>2</tablerow>
    </card>
    <card>
      <name>Chic Medic Sulucchi</name>
      <text>
■ Your Dragons cost 1 less to summon. They can't cost 0 or less.
■ Saver
  </text>
      <prop>
        <maintype>Creature</maintype>
        <type>Armored Fire Bird</type>
        <manacost>2</manacost>
        <colors>Fire</colors>
        <pt>2000</pt>
      </prop>
      <set num="DM23-RP2-43">DM23-RP2</set>
      <related></related>
      <tablerow>2</tablerow>
    </card>
    <card>
      <name>Watt Spike Trappi</name>
      <text>
■ Guard Strike
■ Guardman
■ If you don't have 2 or more Dragons, this creature can't attack.
  </text>
      <prop>
        <maintype>Creature</maintype>
        <type>Armored Fire Bird</type>
        <manacost>1</manacost>
        <colors>Fire</colors>
        <pt>3000</pt>
      </prop>
      <set num="DM23-RP2-44">DM23-RP2</set>
      <related></related>
      <tablerow>2</tablerow>
    </card>
    <card>
      <name>Teeshot Beetle</name>
      <text>
■ Powered Breaker
■ This creature gets +2000 power for each card in each player's hand.
■ This creature can't be blocked by creatures that have less power than this creature.
  </text>
      <prop>
        <maintype>Creature</maintype>
        <type>Giant Insect</type>
        <manacost>5</manacost>
        <colors>Nature</colors>
        <pt>2000+</pt>
      </prop>
      <set num="DM23-RP2-46">DM23-RP2</set>
      <related></related>
      <tablerow>2</tablerow>
    </card>
    <card>
      <name>Oshikatsu Giant</name>
      <text>
■ Whenever you put the second card into your mana zone each turn, Giant Mechraid 5. Mechraid
  </text>
      <prop>
        <maintype>Creature</maintype>
        <type>Giant</type>
        <manacost>4</manacost>
        <colors>Nature</colors>
        <pt>5000</pt>
      </prop>
      <set num="DM23-RP2-47">DM23-RP2</set>
      <related></related>
      <tablerow>2</tablerow>
    </card>
    <card>
      <name>PK Faerie</name>
      <text>
■ When your opponent puts their second or subsequent creature this turn, you may put this creature into your mana zone. If you do, put your opponent's creature into it's owner's mana zone.
  </text>
      <prop>
        <maintype>Creature</maintype>
        <type>Giant Snow Faerie</type>
        <manacost>2</manacost>
        <colors>Nature</colors>
        <pt>2000</pt>
      </prop>
      <set num="DM23-RP2-49">DM23-RP2</set>
      <related></related>
      <tablerow>2</tablerow>
    </card>
    <card>
      <name>Toge, Scatter Stone Holy Chaos</name>
      <text>
■ Blocker
■ This creature can't attack players.
  </text>
      <prop>
        <maintype>Creature</maintype>
        <type>Mecha Del Stella/Shinobi</type>
        <manacost>1</manacost>
        <colors>Light</colors>
        <pt>3000</pt>
      </prop>
      <set num="DM23-RP2-54">DM23-RP2</set>
      <related></related>
      <tablerow>2</tablerow>
    </card>
    <card>
      <name>Author-Unknown-Machine/"Magical", Water Summon Spell</name>
      <text>
■ Blocker
■ Powered Blocker
■ Double Breaker
=========================
■ Look at the top 2 cards of your deck. You may reveal a Magic or spell from among them and add it to your hand. Put the rest on the bottom of the deck in any order.
  </text>
      <prop>
        <maintype>Twinpact</maintype>
        <type>Magic Command/Magic Song</type>
        <manacost>5</manacost>
        <colors>Water/Water</colors>
        <pt>6000+</pt>
      </prop>
      <set num="DM23-RP2-56">DM23-RP2</set>
      <related></related>
      <tablerow>2</tablerow>
    </card>
    <card>
      <name>TUBA Crawler</name>
      <text>
■ When you put this creature, choose up to 3 of your opponents creatures. Those creatures can't attack or block until the start of your next turn.
  </text>
      <prop>
        <maintype>Creature</maintype>
        <type>Magic Earth Eater</type>
        <manacost>4</manacost>
        <colors>Water</colors>
        <pt>4000</pt>
      </prop>
      <set num="DM23-RP2-58">DM23-RP2</set>
      <related></related>
      <tablerow>2</tablerow>
    </card>
    <card>
      <name>♪ Why are you leaving, where are you going now</name>
      <text>
■ Choose a player. That player shuffles all cards in their graveyard and puts them on the bottom of their deck.
■ Draw 2 cards.
  </text>
      <prop>
        <maintype>Spell</maintype>
        <type>Magic Song</type>
        <manacost>3</manacost>
        <colors>Water</colors>
        <pt></pt>
      </prop>
      <set num="DM23-RP2-60">DM23-RP2</set>
      <related></related>
      <tablerow>2</tablerow>
    </card>
    <card>
      <name>Sadrain %3D Train/"Abyssal", Jashin Spell</name>
      <text>
■ Abyss Rush
■ Double Breaker
=========================
■ Put the top card of your deck into your graveyard, then return an Abyss from your graveyard to your hand.
  </text>
      <prop>
        <maintype>Twinpact</maintype>
        <type>Abyss Royale/Invitation to the Abyss</type>
        <manacost>5</manacost>
        <colors>Darkness/Darkness</colors>
        <pt>6000</pt>
      </prop>
      <set num="DM23-RP2-61">DM23-RP2</set>
      <related></related>
      <tablerow>2</tablerow>
    </card>
    <card>
      <name>Do:Niwa</name>
      <text>
■ When you put this creature or whenever it attacks, you may put an Abyss creature that costs 3 or less from your graveyard.
  </text>
      <prop>
        <maintype>Creature</maintype>
        <type>Noir Abyss</type>
        <manacost>5</manacost>
        <colors>Darkness</colors>
        <pt>5000</pt>
      </prop>
      <set num="DM23-RP2-62">DM23-RP2</set>
      <related></related>
      <tablerow>2</tablerow>
    </card>
    <card>
      <name>Dopoison, Spray Monster</name>
      <text>
■ When you put this creature, each player chooses one of their creatures and destroys it.
  </text>
      <prop>
        <maintype>Creature</maintype>
        <type>Devil Mask</type>
        <manacost>3</manacost>
        <colors>Darkness</colors>
        <pt>5000</pt>
      </prop>
      <set num="DM23-RP2-63">DM23-RP2</set>
      <related></related>
      <tablerow>2</tablerow>
    </card>
    <card>
      <name>Gu:Lubokassa</name>
      <text>
■ End Step
  </text>
      <prop>
        <maintype>Creature</maintype>
        <type>Noir Abyss</type>
        <manacost>3</manacost>
        <colors>Darkness</colors>
        <pt>4000</pt>
      </prop>
      <set num="DM23-RP2-64">DM23-RP2</set>
      <related></related>
      <tablerow>2</tablerow>
    </card>
    <card>
      <name>Genji Amatsu Powercchi/"Armorado", Summon Fire Spell</name>
      <text>
■ Power Attacker
■ Double Breaker
=========================
■ If you have a Fire Bird, look at the top 4 cards of your deck. Otherwise, look at the top card of your deck. You may reveal an Armored card from among them to your opponent and add it to your hand. Put the rest on the bottom of your deck in any order.
  </text>
      <prop>
        <maintype>Twinpact</maintype>
        <type>Armored Fire Bird/</type>
        <manacost>5</manacost>
        <colors>Fire/Fire</colors>
        <pt>4000+</pt>
      </prop>
      <set num="DM23-RP2-66">DM23-RP2</set>
      <related></related>
      <tablerow>2</tablerow>
    </card>
    <card>
      <name>Parlen Flare Iyeppi</name>
      <text>
■ Speed Attacker
■ End Step
  </text>
      <prop>
        <maintype>Creature</maintype>
        <type>Armored Fire Bird</type>
        <manacost>4</manacost>
        <colors>Fire</colors>
        <pt>3000</pt>
      </prop>
      <set num="DM23-RP2-67">DM23-RP2</set>
      <related></related>
      <tablerow>2</tablerow>
    </card>
    <card>
      <name>Achikochi Naru Pippi</name>
      <text>
■ When you put this creature, choose one of the following.
:► Choose one of your opponent's creatures that has "blocker" and destroy it.
:► Draw a card.
  </text>
      <prop>
        <maintype>Creature</maintype>
        <type>Armored Fire Bird</type>
        <manacost>3</manacost>
        <colors>Fire</colors>
        <pt>3000</pt>
      </prop>
      <set num="DM23-RP2-68">DM23-RP2</set>
      <related></related>
      <tablerow>2</tablerow>
    </card>
    <card>
      <name>Achikochi Naru Pippi</name>
      <text>
■ When you put this creature, choose one of the following.
:► Choose one of your opponent's creatures that has "blocker" and destroy it.
:► Draw a card.
  </text>
      <prop>
        <maintype>Creature</maintype>
        <type>Armored Fire Bird</type>
        <manacost>3</manacost>
        <colors>Fire</colors>
        <pt>3000</pt>
      </prop>
      <set num="DM23-RP2- 21B">DM23-RP2</set>
      <related></related>
      <tablerow>2</tablerow>
    </card>
    <card>
      <name>Achikochi Naru Pippi</name>
      <text>
■ When you put this creature, choose one of the following.
:► Choose one of your opponent's creatures that has "blocker" and destroy it.
:► Draw a card.
  </text>
      <prop>
        <maintype>Creature</maintype>
        <type>Armored Fire Bird</type>
        <manacost>3</manacost>
        <colors>Fire</colors>
        <pt>3000</pt>
      </prop>
      <set num="DM23-RP2- 19A">DM23-RP2</set>
      <related></related>
      <tablerow>2</tablerow>
    </card>
    <card>
      <name>Marauder "Gai" Drive</name>
      <text>
■ Speed Attacker
  </text>
      <prop>
        <maintype>Creature</maintype>
        <type>Armored Dragonoid</type>
        <manacost>2</manacost>
        <colors>Fire</colors>
        <pt>1000</pt>
      </prop>
      <set num="DM23-RP2-69">DM23-RP2</set>
      <related></related>
      <tablerow>2</tablerow>
    </card>
    <card>
      <name>Kankuro Faerie/"Jaibaban", Summon Nature Spell</name>
      <text>
■ Guardman
■ Double Breaker
=========================
■ Put the top card of your deck into your mana zone. Then you may return a Giant from your mana zone to your hand.
  </text>
      <prop>
        <maintype>Twinpact</maintype>
        <type>Giant Snow Faerie/Giant Skill</type>
        <manacost>5</manacost>
        <colors>Nature/Nature</colors>
        <pt>8000</pt>
      </prop>
      <set num="DM23-RP2-71">DM23-RP2</set>
      <related></related>
      <tablerow>2</tablerow>
    </card>
    <card>
      <name>Parputt Scarab</name>
      <text>
■ Mach Fighter
  </text>
      <prop>
        <maintype>Creature</maintype>
        <type>Giant Insect</type>
        <manacost>3</manacost>
        <colors>Nature</colors>
        <pt>5000</pt>
      </prop>
      <set num="DM23-RP2-72">DM23-RP2</set>
      <related></related>
      <tablerow>2</tablerow>
    </card>
    <card>
      <name>Halftime Faerie</name>
      <text>
■ Whenever this creature attacks a player, put this creature into your mana zone.
  </text>
      <prop>
        <maintype>Creature</maintype>
        <type>Giant Snow Faerie</type>
        <manacost>2</manacost>
        <colors>Nature</colors>
        <pt>6000</pt>
      </prop>
      <set num="DM23-RP2-73">DM23-RP2</set>
      <related></related>
      <tablerow>2</tablerow>
    </card>
  </cards>
</cockatrice_carddatabase>