<cockatrice_carddatabase version="4">
  <sets>
    <set>
      <name>DMC-43</name>
      <longname>DMC-43</longname>
      <settype>DMC-43</settype>
      <releasedate>2023-11-05</releasedate>
    </set>
  </sets>
  <cards>
    <card>
      <name>Alcadeias, Lord of Spirits</name>
      <text>
■ Evolution—Put on one of your Angel Commands.
■ Double Breaker
■ Players can't cast spells other than light spells.
  </text>
      <prop>
        <maintype>Evolution Creature</maintype>
        <type>Angel Command</type>
        <manacost>6</manacost>
        <colors>Light</colors>
        <pt>12500</pt>
      </prop>
      <set num="DMC-43-14">DMC-43</set>
      <related></related>
      <tablerow>2</tablerow>
    </card>
    <card>
      <name>Magmadragon Jagalzor</name>
      <text>
■ Double Breaker
■ Turbo Rush
  </text>
      <prop>
        <maintype>Creature</maintype>
        <type>Volcano Dragon</type>
        <manacost>6</manacost>
        <colors>Fire</colors>
        <pt>6000</pt>
      </prop>
      <set num="DMC-43-20">DMC-43</set>
      <related></related>
      <tablerow>2</tablerow>
    </card>
    <card>
      <name>Petrova, Channeler of Suns</name>
      <text>
■ When you put this creature into the battle zone, choose a race other than Mecha Del Sol. Each creature of that race gets +4000 power.
■ Whenever your opponent would choose a creature in the battle zone, he Unchoosable
  </text>
      <prop>
        <maintype>Creature</maintype>
        <type>Mecha Del Sol</type>
        <manacost>5</manacost>
        <colors>Light</colors>
        <pt>3500</pt>
      </prop>
      <set num="DMC-43-8">DMC-43</set>
      <related></related>
      <tablerow>2</tablerow>
    </card>
    <card>
      <name>Asylum, Elemental Dragon Knight</name>
      <text>
■ Multi
■ Sympathy
■ Double Breaker
■ When this creature would be destroyed, add it to your shields face down instead.
  </text>
      <prop>
        <maintype>Creature</maintype>
        <type>Angel Command/Armored Dragon</type>
        <manacost>6</manacost>
        <colors>Light/Fire</colors>
        <pt>6000</pt>
      </prop>
      <set num="DMC-43-12">DMC-43</set>
      <related></related>
      <tablerow>2</tablerow>
    </card>
    <card>
      <name>Hell's Scrapper</name>
      <text>
■ Shield Trigger
■ Destroy any number of your opponent's creatures that have total power 5000 or less.
  </text>
      <prop>
        <maintype>Spell</maintype>
        <type></type>
        <manacost>7</manacost>
        <colors>Fire</colors>
        <pt></pt>
      </prop>
      <set num="DMC-43-28">DMC-43</set>
      <related></related>
      <tablerow>2</tablerow>
    </card>
    <card>
      <name>Valiant Spark</name>
      <text>
■ Shield Trigger
■ Choose one of your opponent's creatures in the battle zone and tap it.
■ Metamorph
  </text>
      <prop>
        <maintype>Spell</maintype>
        <type></type>
        <manacost>3</manacost>
        <colors>Light</colors>
        <pt></pt>
      </prop>
      <set num="DMC-43-22">DMC-43</set>
      <related></related>
      <tablerow>2</tablerow>
    </card>
    <card>
      <name>Super Spark</name>
      <text>
■ Shield Trigger
■ Tap all your opponent's creatures in the battle zone.
  </text>
      <prop>
        <maintype>Spell</maintype>
        <type></type>
        <manacost>5</manacost>
        <colors>Light</colors>
        <pt></pt>
      </prop>
      <set num="DMC-43-21">DMC-43</set>
      <related></related>
      <tablerow>2</tablerow>
    </card>
    <card>
      <name>Bolmeteus Musha Dragon</name>
      <text>
■ Double Breaker
■ Whenever this creature attacks, you may put one of your shields into your graveyard. If you do, destroy one of your opponent's creatures that has power 6000 or less.
  </text>
      <prop>
        <maintype>Creature</maintype>
        <type>Armored Dragon</type>
        <manacost>6</manacost>
        <colors>Fire</colors>
        <pt>6000</pt>
      </prop>
      <set num="DMC-43-11">DMC-43</set>
      <related></related>
      <tablerow>2</tablerow>
    </card>
    <card>
      <name>Musha Lupia</name>
      <text>
■ Multi
■ Your creatures that have Dragon in their race each cost 1 less to summon. They can't cost less than 1.
■ Whenever your "tooltip
  </text>
      <prop>
        <maintype>Creature</maintype>
        <type>Fire Bird</type>
        <manacost>4</manacost>
        <colors>Light/Fire</colors>
        <pt>2000</pt>
      </prop>
      <set num="DMC-43-29">DMC-43</set>
      <related></related>
      <tablerow>2</tablerow>
    </card>
    <card>
      <name>Flameburn Dragon</name>
      <text>
■ When you put this creature into the battle zone, destroy one of your opponent's creatures that has power 4000 or less.
  </text>
      <prop>
        <maintype>Creature</maintype>
        <type>Armored Dragon</type>
        <manacost>6</manacost>
        <colors>Fire</colors>
        <pt>5000</pt>
      </prop>
      <set num="DMC-43-2">DMC-43</set>
      <related></related>
      <tablerow>2</tablerow>
    </card>
    <card>
      <name>Saint Bolshack, Elemental Dragon Knight</name>
      <text>
■ Multi
■ This creature costs 1 less to summon for each Angel Command and Armored Dragon in your graveyard. It can't cost less than 2.
■ Speed Attacker
■ Power Attacker
■ Double Breaker
  </text>
      <prop>
        <maintype>Creature</maintype>
        <type>Angel Command/Armored Dragon</type>
        <manacost>9</manacost>
        <colors>Light/Fire</colors>
        <pt>9000+</pt>
      </prop>
      <set num="DMC-43-3">DMC-43</set>
      <related></related>
      <tablerow>2</tablerow>
    </card>
    <card>
      <name>Ulpheus, Dragonic Elemental</name>
      <text>
■ When you put this creature into the battle zone, if you have at least one Dragon or Angel Command in your graveyard, you may cast a spell that has "shield trigger" from your hand For No Cost
■ Double Breaker
  </text>
      <prop>
        <maintype>Creature</maintype>
        <type>Apollonia Dragon/Angel Command</type>
        <manacost>7</manacost>
        <colors>Light</colors>
        <pt>6000</pt>
      </prop>
      <set num="DMC-43-7">DMC-43</set>
      <related></related>
      <tablerow>2</tablerow>
    </card>
    <card>
      <name>Pop Rubin</name>
      <text>
■ Tap Ability
  </text>
      <prop>
        <maintype>Creature</maintype>
        <type>Fire Bird</type>
        <manacost>2</manacost>
        <colors>Fire</colors>
        <pt>1000</pt>
      </prop>
      <set num="DMC-43-37">DMC-43</set>
      <related></related>
      <tablerow>2</tablerow>
    </card>
    <card>
      <name>Endra Pappi</name>
      <text>
■ Multi
■ Whenever you put an Angel Command or a Dragon into the battle zone, you may draw a card.
  </text>
      <prop>
        <maintype>Creature</maintype>
        <type>Fire Bird</type>
        <manacost>3</manacost>
        <colors>Light/Fire</colors>
        <pt>1000</pt>
      </prop>
      <set num="DMC-43-4">DMC-43</set>
      <related></related>
      <tablerow>2</tablerow>
    </card>
    <card>
      <name>Ambitious Dragon</name>
      <text>
■ This creature gets +2000 power for each of your Fire Birds in the battle zone. 
■ While you have a Fire Bird in the battle zone, this creature has "double breaker".
  </text>
      <prop>
        <maintype>Creature</maintype>
        <type>Armored Dragon</type>
        <manacost>5</manacost>
        <colors>Fire</colors>
        <pt>4000+</pt>
      </prop>
      <set num="DMC-43-34">DMC-43</set>
      <related></related>
      <tablerow>2</tablerow>
    </card>
    <card>
      <name>Ultimus, Divine Law Elemental</name>
      <text>
■ Blocker
■ This creature can't attack players.
■ When this creature is destroyed, search your deck. You may take a spell that has "Shield Trigger" from your deck, show that spell to your opponent, and put it into your hand. Then shuffle your deck.
  </text>
      <prop>
        <maintype>Creature</maintype>
        <type>Angel Command</type>
        <manacost>4</manacost>
        <colors>Light</colors>
        <pt>3500</pt>
      </prop>
      <set num="DMC-43-32">DMC-43</set>
      <related></related>
      <tablerow>2</tablerow>
    </card>
    <card>
      <name>Seventh, Light Divine Dragon</name>
      <text>
■ Each of your Dragons in the battle zone gets "blocker".
  </text>
      <prop>
        <maintype>Creature</maintype>
        <type>Apollonia Dragon</type>
        <manacost>6</manacost>
        <colors>Light</colors>
        <pt>5500</pt>
      </prop>
      <set num="DMC-43-31">DMC-43</set>
      <related></related>
      <tablerow>2</tablerow>
    </card>
    <card>
      <name>Elementius Thunderbolt Dragon</name>
      <text>
■ While you have no shields, this creature gets "speed attacker".
■ When your last shield is broken, before you break that shield destroy one of your opponent's creatures that has power 4000 or less.
■ When your last shield is put into your graveyard, before you put that shield into your graveyard, destroy one of your opponent's creatures that has power 4000 or less.
■ Double Breaker
  </text>
      <prop>
        <maintype>Creature</maintype>
        <type>Armored Dragon</type>
        <manacost>7</manacost>
        <colors>Fire</colors>
        <pt>6000</pt>
      </prop>
      <set num="DMC-43-19">DMC-43</set>
      <related></related>
      <tablerow>2</tablerow>
    </card>
  </cards>
</cockatrice_carddatabase>